Workbook

Sheet Dashboard
A1: EXECUTIVE FINANCIAL DASHBOARD | Nandini FoodWorks | FY 2024-25 (with FY 2025-26 H1 Forecast)
A3: ACTUAL REVENUE | D3: BUDGET REVENUE | G3: REVENUE VARIANCE | J3: ACTUAL EXPENSES (incl. COGS)
A4: ='Budget vs Actual'!D16 -> 35560258 | D4: ='Budget vs Actual'!C16 -> 35684850 | G4: ='Budget vs Actual'!E16 -> -124591.54 | J4: ='Budget vs Actual'!I16 -> 29691261
A6: BUDGET EXPENSES (incl. COGS) | D6: EXPENSE VARIANCE | G6: GROSS PROFIT (Actual) | J6: NET PROFIT (Actual)
A7: ='Budget vs Actual'!H16 -> 29638173 | D7: ='Budget vs Actual'!J16 -> 53088.287 | G7: ='Budget vs Actual'!D16-SUM('Revenue Planning'!P4:P51) -> 13265308 | J7: ='Budget vs Actual'!N16 -> 5868997
A9: NET PROFIT MARGIN % | D9: FORECAST REVENUE (Apr-Sep 25) | G9: FORECAST PROFIT (Apr-Sep 25) | J9: BUDGET ACHIEVEMENT % (Revenue)
A10: =IFERROR('Budget vs Actual'!N16/'Budget vs Actual'!D16,"") -> 0.16504371 | D10: ='Financial Forecast'!C18 -> 19118727 | G10: ='Financial Forecast'!E18 -> 3248750.2 | J10: =IFERROR('Budget vs Actual'!D16/'Budget vs Actual'!C16,"") -> 0.99650856
A16: Chart Data (formula-linked - do not delete; charts reference these cells)
A17: Month | B17: Budget Revenue | C17: Actual Revenue | D17: Budget Expense | E17: Actual Expense | F17: Budget Profit | G17: Actual Profit | H17: Revenue Variance | I17: Actual Net Margin % | J17: Budget Net Margin %
A18: ='Budget vs Actual'!A4 -> Apr-24 | B18: ='Budget vs Actual'!C4 -> 2861000 | C18: ='Budget vs Actual'!D4 -> 2874061.9 | D18: ='Budget vs Actual'!H4 -> 2371400 | E18: ='Budget vs Actual'!I4 -> 2371148.5 | F18: ='Budget vs Actual'!M4 -> 489600 | G18: ='Budget vs Actual'!N4 -> 502913.45 | H18: ='Budget vs Actual'!E4 -> 13061.94 | I18: =IFERROR(G18/C18,"") -> 0.17498351 | J18: =IFERROR(F18/B18,"") -> 0.17112898
A19: ='Budget vs Actual'!A5 -> May-24 | B19: ='Budget vs Actual'!C5 -> 2978440.7 | C19: ='Budget vs Actual'!D5 -> 2956844.2 | D19: ='Budget vs Actual'!H5 -> 2446171.9 | E19: ='Budget vs Actual'!I5 -> 2437711.1 | F19: ='Budget vs Actual'!M5 -> 532268.8 | G19: ='Budget vs Actual'!N5 -> 519133.09 | H19: ='Budget vs Actual'!E5 -> -21596.51 | I19: =IFERROR(G19/C19,"") -> 0.17556999 | J19: =IFERROR(F19/B19,"") -> 0.1787072
A20: ='Budget vs Actual'!A6 -> Jun-24 | B20: ='Budget vs Actual'!C6 -> 2943903.8 | C20: ='Budget vs Actual'!D6 -> 2920238.2 | D20: ='Budget vs Actual'!H6 -> 2429053.6 | E20: ='Budget vs Actual'!I6 -> 2447489 | F20: ='Budget vs Actual'!M6 -> 514850.2 | G20: ='Budget vs Actual'!N6 -> 472749.28 | H20: ='Budget vs Actual'!E6 -> -23665.52 | I20: =IFERROR(G20/C20,"") -> 0.16188723 | J20: =IFERROR(F20/B20,"") -> 0.1748869
A21: ='Budget vs Actual'!A7 -> Jul-24 | B21: ='Budget vs Actual'!C7 -> 2742367 | C21: ='Budget vs Actual'!D7 -> 2661268.9 | D21: ='Budget vs Actual'!H7 -> 2312882.6 | E21: ='Budget vs Actual'!I7 -> 2300692 | F21: ='Budget vs Actual'!M7 -> 429484.43 | G21: ='Budget vs Actual'!N7 -> 360576.85 | H21: ='Budget vs Actual'!E7 -> -81098.12 | I21: =IFERROR(G21/C21,"") -> 0.13549057 | J21: =IFERROR(F21/B21,"") -> 0.15661085
A22: ='Budget vs Actual'!A8 -> Aug-24 | B22: ='Budget vs Actual'!C8 -> 2743148.7 | C22: ='Budget vs Actual'!D8 -> 2611563.2 | D22: ='Budget vs Actual'!H8 -> 2317691.4 | E22: ='Budget vs Actual'!I8 -> 2282909.8 | F22: ='Budget vs Actual'!M8 -> 425457.33 | G22: ='Budget vs Actual'!N8 -> 328653.39 | H22: ='Budget vs Actual'!E8 -> -131585.54 | I22: =IFERROR(G22/C22,"") -> 0.12584547 | J22: =IFERROR(F22/B22,"") -> 0.15509817
A23: ='Budget vs Actual'!A9 -> Sep-24 | B23: ='Budget vs Actual'!C9 -> 2843333.8 | C23: ='Budget vs Actual'!D9 -> 2826123.7 | D23: ='Budget vs Actual'!H9 -> 2383317.2 | E23: ='Budget vs Actual'!I9 -> 2364068.3 | F23: ='Budget vs Actual'!M9 -> 460016.58 | G23: ='Budget vs Actual'!N9 -> 462055.41 | H23: ='Budget vs Actual'!E9 -> -17210.14 | I23: =IFERROR(G23/C23,"") -> 0.1634944 | J23: =IFERROR(F23/B23,"") -> 0.16178775
A24: ='Budget vs Actual'!A10 -> Oct-24 | B24: ='Budget vs Actual'!C10 -> 3308101.5 | C24: ='Budget vs Actual'!D10 -> 3579618.2 | D24: ='Budget vs Actual'!H10 -> 2705340.5 | E24: ='Budget vs Actual'!I10 -> 2869470.4 | F24: ='Budget vs Actual'!M10 -> 602760.95 | G24: ='Budget vs Actual'!N10 -> 710147.88 | H24: ='Budget vs Actual'!E10 -> 271516.74 | I24: =IFERROR(G24/C24,"") -> 0.19838649 | J24: =IFERROR(F24/B24,"") -> 0.18220751
A25: ='Budget vs Actual'!A11 -> Nov-24 | B25: ='Budget vs Actual'!C11 -> 3456789.7 | C25: ='Budget vs Actual'!D11 -> 3669694.4 | D25: ='Budget vs Actual'!H11 -> 2804484.3 | E25: ='Budget vs Actual'!I11 -> 2932697 | F25: ='Budget vs Actual'!M11 -> 652305.33 | G25: ='Budget vs Actual'!N11 -> 736997.43 | H25: ='Budget vs Actual'!E11 -> 212904.72 | I25: =IFERROR(G25/C25,"") -> 0.20083346 | J25: =IFERROR(F25/B25,"") -> 0.18870264
A26: ='Budget vs Actual'!A12 -> Dec-24 | B26: ='Budget vs Actual'!C12 -> 3144592.9 | C26: ='Budget vs Actual'!D12 -> 3131491 | D26: ='Budget vs Actual'!H12 -> 2581234.8 | E26: ='Budget vs Actual'!I12 -> 2563750 | F26: ='Budget vs Actual'!M12 -> 563358.06 | G26: ='Budget vs Actual'!N12 -> 567740.97 | H26: ='Budget vs Actual'!E12 -> -13101.9 | I26: =IFERROR(G26/C26,"") -> 0.18130053 | J26: =IFERROR(F26/B26,"") -> 0.17915135
A27: ='Budget vs Actual'!A13 -> Jan-25 | B27: ='Budget vs Actual'!C13 -> 2770198.7 | C27: ='Budget vs Actual'!D13 -> 2469819.4 | D27: ='Budget vs Actual'!H13 -> 2354496.4 | E27: ='Budget vs Actual'!I13 -> 2206679.6 | F27: ='Budget vs Actual'!M13 -> 415702.25 | G27: ='Budget vs Actual'!N13 -> 263139.73 | H27: ='Budget vs Actual'!E13 -> -300379.31 | I27: =IFERROR(G27/C27,"") -> 0.1065421 | J27: =IFERROR(F27/B27,"") -> 0.15006225
A28: ='Budget vs Actual'!A14 -> Feb-25 | B28: ='Budget vs Actual'!C14 -> 2836900.5 | C28: ='Budget vs Actual'!D14 -> 2830605.6 | D28: ='Budget vs Actual'!H14 -> 2397655.3 | E28: ='Budget vs Actual'!I14 -> 2390328.8 | F28: ='Budget vs Actual'!M14 -> 439245.23 | G28: ='Budget vs Actual'!N14 -> 440276.81 | H28: ='Budget vs Actual'!E14 -> -6294.88 | I28: =IFERROR(G28/C28,"") -> 0.15554156 | J28: =IFERROR(F28/B28,"") -> 0.15483279
A29: ='Budget vs Actual'!A15 -> Mar-25 | B29: ='Budget vs Actual'!C15 -> 3056072.8 | C29: ='Budget vs Actual'!D15 -> 3028929.7 | D29: ='Budget vs Actual'!H15 -> 2534445.1 | E29: ='Budget vs Actual'!I15 -> 2524317 | F29: ='Budget vs Actual'!M15 -> 521627.7 | G29: ='Budget vs Actual'!N15 -> 504612.76 | H29: ='Budget vs Actual'!E15 -> -27143.02 | I29: =IFERROR(G29/C29,"") -> 0.16659771 | J29: =IFERROR(F29/B29,"") -> 0.17068563
A31: Actual + Forecast Revenue Trend (18 months)
A32: Month | B32: Revenue
A33: ='Budget vs Actual'!A4 -> Apr-24 | B33: ='Budget vs Actual'!D4 -> 2874061.9
A34: ='Budget vs Actual'!A5 -> May-24 | B34: ='Budget vs Actual'!D5 -> 2956844.2
A35: ='Budget vs Actual'!A6 -> Jun-24 | B35: ='Budget vs Actual'!D6 -> 2920238.2
A36: ='Budget vs Actual'!A7 -> Jul-24 | B36: ='Budget vs Actual'!D7 -> 2661268.9
A37: ='Budget vs Actual'!A8 -> Aug-24 | B37: ='Budget vs Actual'!D8 -> 2611563.2
A38: ='Budget vs Actual'!A9 -> Sep-24 | B38: ='Budget vs Actual'!D9 -> 2826123.7
A39: ='Budget vs Actual'!A10 -> Oct-24 | B39: ='Budget vs Actual'!D10 -> 3579618.2
A40: ='Budget vs Actual'!A11 -> Nov-24 | B40: ='Budget vs Actual'!D11 -> 3669694.4
A41: ='Budget vs Actual'!A12 -> Dec-24 | B41: ='Budget vs Actual'!D12 -> 3131491
A42: ='Budget vs Actual'!A13 -> Jan-25 | B42: ='Budget vs Actual'!D13 -> 2469819.4
A43: ='Budget vs Actual'!A14 -> Feb-25 | B43: ='Budget vs Actual'!D14 -> 2830605.6
A44: ='Budget vs Actual'!A15 -> Mar-25 | B44: ='Budget vs Actual'!D15 -> 3028929.7
A45: ='Financial Forecast'!A12 -> Apr-25 | B45: ='Financial Forecast'!C12 -> 3072815.8
A46: ='Financial Forecast'!A13 -> May-25 | B46: ='Financial Forecast'!C13 -> 3117364
A47: ='Financial Forecast'!A14 -> Jun-25 | B47: ='Financial Forecast'!C14 -> 3162584.6
A48: ='Financial Forecast'!A15 -> Jul-25 | B48: ='Financial Forecast'!C15 -> 3208488.3
A49: ='Financial Forecast'!A16 -> Aug-25 | B49: ='Financial Forecast'!C16 -> 3255085.9
A50: ='Financial Forecast'!A17 -> Sep-25 | B50: ='Financial Forecast'!C17 -> 3302388.2
A52: Expense Category Variance (Rs.)
A53: Category | B53: Variance
A54: ='Expense Budget'!A117 -> Salaries | B54: ='Expense Budget'!F117 -> 16626
A55: ='Expense Budget'!A118 -> Rent | B55: ='Expense Budget'!F118 -> 37
A56: ='Expense Budget'!A119 -> Utilities | B56: ='Expense Budget'!F119 -> 7558
A57: ='Expense Budget'!A120 -> Marketing | B57: ='Expense Budget'!F120 -> 11305
A58: ='Expense Budget'!A121 -> Technology | B58: ='Expense Budget'!F121 -> 3417
A59: ='Expense Budget'!A122 -> Transportation | B59: ='Expense Budget'!F122 -> 3631
A60: ='Expense Budget'!A123 -> Office Expenses | B60: ='Expense Budget'!F123 -> 4427
A61: ='Expense Budget'!A124 -> Maintenance | B61: ='Expense Budget'!F124 -> 33
A62: ='Expense Budget'!A125 -> Other Operating Expenses | B62: ='Expense Budget'!F125 -> 480
A64: Revenue by Category (Actual, Rs.)
A65: Category | B65: Actual Revenue
A66: ='Revenue Planning'!A81 -> Packaged Snacks | B66: ='Revenue Planning'!G81 -> 10554798
A67: ='Revenue Planning'!A82 -> Beverages | B67: ='Revenue Planning'!G82 -> 8623347.8
A68: ='Revenue Planning'!A83 -> Dairy Products | B68: ='Revenue Planning'!G83 -> 10596560
A69: ='Revenue Planning'!A84 -> Bakery Items | B69: ='Revenue Planning'!G84 -> 5785552.4
A118: Filters: use the AutoFilter dropdowns on the Revenue Planning and Expense Budget sheets to filter by Month, Quarter, Revenue Category or Expense Category. Chart data above updates automatically from Budget vs Actual / Financial Forecast / Revenue Planning / Expense Budget - it is not a separate manual dataset.

Sheet Revenue Planning
A1: REVENUE PLANNING | Nandini FoodWorks | FY 2024-25 (Budget vs Actual) + FY 2025-26 Forecast (Apr-Sep)
A3: Month | B3: Quarter | C3: Category | D3: Budget Volume (units) | E3: Budget ASP (Rs.) | F3: Budget Revenue (Rs.) | G3: Actual Volume (units) | H3: Actual ASP (Rs.) | I3: Actual Revenue (Rs.) | J3: Forecast Revenue (Rs.) | K3: Revenue Variance (Rs.) | L3: Revenue Variance % | M3: Budget COGS Rate % | N3: Budget COGS (Rs.) | O3: Actual COGS Rate % | P3: Actual COGS (Rs.) | Q3: Forecast COGS (Rs.)
A4: Apr-24 | B4: Q1 | C4: Packaged Snacks | D4: 18000 | E4: 45 | F4: =D4*E4 -> 810000 | G4: 18179 | H4: 44.97 | I4: =G4*H4 -> 817509.63 | K4: =IF(F4=0,"",I4-F4) -> 7509.63 | L4: =IFERROR(K4/F4,"") -> 0.0092711481 | M4: 0.62 | N4: =F4*M4 -> 502200 | O4: 0.6174 | P4: =I4*O4 -> 504730.45
A5: Apr-24 | B5: Q1 | C5: Beverages | D5: 27500 | E5: 28 | F5: =D5*E5 -> 770000 | G5: 27376 | H5: 28.01 | I5: =G5*H5 -> 766801.76 | K5: =IF(F5=0,"",I5-F5) -> -3198.24 | L5: =IFERROR(K5/F5,"") -> -0.0041535584 | M5: 0.58 | N5: =F5*M5 -> 446600 | O5: 0.5716 | P5: =I5*O5 -> 438303.89
A6: Apr-24 | B6: Q1 | C6: Dairy Products | D6: 15000 | E6: 55 | F6: =D6*E6 -> 825000 | G6: 15222 | H6: 55.05 | I6: =G6*H6 -> 837971.1 | K6: =IF(F6=0,"",I6-F6) -> 12971.1 | L6: =IFERROR(K6/F6,"") -> 0.015722545 | M6: 0.68 | N6: =F6*M6 -> 561000 | O6: 0.6781 | P6: =I6*O6 -> 568228.2
A7: Apr-24 | B7: Q1 | C7: Bakery Items | D7: 12000 | E7: 38 | F7: =D7*E7 -> 456000 | G7: 11955 | H7: 37.79 | I7: =G7*H7 -> 451779.45 | K7: =IF(F7=0,"",I7-F7) -> -4220.55 | L7: =IFERROR(K7/F7,"") -> -0.0092555921 | M7: 0.6 | N7: =F7*M7 -> 273600 | O7: 0.5996 | P7: =I7*O7 -> 270886.96
A8: May-24 | B8: Q1 | C8: Packaged Snacks | D8: 18470 | E8: 45.09 | F8: =D8*E8 -> 832812.3 | G8: 18709 | H8: 45.43 | I8: =G8*H8 -> 849949.87 | K8: =IF(F8=0,"",I8-F8) -> 17137.57 | L8: =IFERROR(K8/F8,"") -> 0.02057795 | M8: 0.62 | N8: =F8*M8 -> 516343.63 | O8: 0.6243 | P8: =I8*O8 -> 530623.7
A9: May-24 | B9: Q1 | C9: Beverages | D9: 30180 | E9: 28.06 | F9: =D9*E9 -> 846850.8 | G9: 29320 | H9: 27.98 | I9: =G9*H9 -> 820373.6 | K9: =IF(F9=0,"",I9-F9) -> -26477.2 | L9: =IFERROR(K9/F9,"") -> -0.031265484 | M9: 0.58 | N9: =F9*M9 -> 491173.46 | O9: 0.5761 | P9: =I9*O9 -> 472617.23
A10: May-24 | B10: Q1 | C10: Dairy Products | D10: 15392 | E10: 55.11 | F10: =D10*E10 -> 848253.12 | G10: 15356 | H10: 55.03 | I10: =G10*H10 -> 845040.68 | K10: =IF(F10=0,"",I10-F10) -> -3212.44 | L10: =IFERROR(K10/F10,"") -> -0.0037871243 | M10: 0.68 | N10: =F10*M10 -> 576812.12 | O10: 0.6848 | P10: =I10*O10 -> 578683.86
A11: May-24 | B11: Q1 | C11: Bakery Items | D11: 11831 | E11: 38.08 | F11: =D11*E11 -> 450524.48 | G11: 11548 | H11: 38.23 | I11: =G11*H11 -> 441480.04 | K11: =IF(F11=0,"",I11-F11) -> -9044.44 | L11: =IFERROR(K11/F11,"") -> -0.020075358 | M11: 0.6 | N11: =F11*M11 -> 270314.69 | O11: 0.586 | P11: =I11*O11 -> 258707.3
A12: Jun-24 | B12: Q1 | C12: Packaged Snacks | D12: 18762 | E12: 45.18 | F12: =D12*E12 -> 847667.16 | G12: 18674 | H12: 45.13 | I12: =G12*H12 -> 842757.62 | K12: =IF(F12=0,"",I12-F12) -> -4909.54 | L12: =IFERROR(K12/F12,"") -> -0.0057918252 | M12: 0.62 | N12: =F12*M12 -> 525553.64 | O12: 0.6377 | P12: =I12*O12 -> 537426.53
A13: Jun-24 | B13: Q1 | C13: Beverages | D13: 29095 | E13: 28.11 | F13: =D13*E13 -> 817860.45 | G13: 29160 | H13: 27.95 | I13: =G13*H13 -> 815022 | K13: =IF(F13=0,"",I13-F13) -> -2838.45 | L13: =IFERROR(K13/F13,"") -> -0.0034705799 | M13: 0.58 | N13: =F13*M13 -> 474359.06 | O13: 0.5753 | P13: =I13*O13 -> 468882.16
A14: Jun-24 | B14: Q1 | C14: Dairy Products | D14: 15180 | E14: 55.22 | F14: =D14*E14 -> 838239.6 | G14: 14731 | H14: 55.02 | I14: =G14*H14 -> 810499.62 | K14: =IF(F14=0,"",I14-F14) -> -27739.98 | L14: =IFERROR(K14/F14,"") -> -0.033093139 | M14: 0.68 | N14: =F14*M14 -> 570002.93 | O14: 0.7026 | P14: =I14*O14 -> 569457.03
A15: Jun-24 | B15: Q1 | C15: Bakery Items | D15: 11537 | E15: 38.15 | F15: =D15*E15 -> 440136.55 | G15: 11850 | H15: 38.14 | I15: =G15*H15 -> 451959 | K15: =IF(F15=0,"",I15-F15) -> 11822.45 | L15: =IFERROR(K15/F15,"") -> 0.026860869 | M15: 0.6 | N15: =F15*M15 -> 264081.93 | O15: 0.6137 | P15: =I15*O15 -> 277367.24
... A51: Mar-25 | B51: Q4 | C51: Bakery Items | D51: 12792 | E51: 38.84 | F51: =D51*E51 -> 496841.28 | G51: 12815 | H51: 38.45 | I51: =G51*H51 -> 492736.75 | K51: =IF(F51=0,"",I51-F51) -> -4104.53 | L51: =IFERROR(K51/F51,"") -> -0.00826125 | M51: 0.6 | N51: =F51*M51 -> 298104.77 | O51: 0.5932 | P51: =I51*O51 -> 292291.44
A52: Apr-25 | B52: Q1 | C52: Packaged Snacks | J52: 877502.79 | Q52: 545877.11
A53: Apr-25 | B53: Q1 | C53: Beverages | J53: 766767.65 | Q53: 440478.38
A54: Apr-25 | B54: Q1 | C54: Dairy Products | J54: 925940.55 | Q54: 636436.6
A55: Apr-25 | B55: Q1 | C55: Bakery Items | J55: 502604.83 | Q55: 304558.97
A56: May-25 | B56: Q1 | C56: Packaged Snacks | J56: 891351.56 | Q56: 554492.15
A57: May-25 | B57: Q1 | C57: Beverages | J57: 775526.57 | Q57: 445510.05
A58: May-25 | B58: Q1 | C58: Dairy Products | J58: 937815.29 | Q58: 644598.59
A59: May-25 | B59: Q1 | C59: Bakery Items | J59: 512670.54 | Q59: 310658.4
A60: Jun-25 | B60: Q1 | C60: Packaged Snacks | J60: 905418.89 | Q60: 563243.16
A61: Jun-25 | B61: Q1 | C61: Beverages | J61: 784385.55 | Q61: 450599.19
A62: Jun-25 | B62: Q1 | C62: Dairy Products | J62: 949842.32 | Q62: 652865.26
A63: Jun-25 | B63: Q1 | C63: Bakery Items | J63: 522937.83 | Q63: 316879.98
... A75: Sep-25 | B75: Q2 | C75: Bakery Items | J75: 554990.01 | Q75: 336302.36
A77: Note: Forecast Revenue is populated only for Apr-25 to Sep-25 (see Financial Forecast sheet for method). Budget/Actual Volume, ASP and COGS are historical FY 2024-25 inputs (blue cells); all Revenue and COGS amounts are formulas (black).
A79: Summary by Revenue Category (FY 2024-25)
A80: Category | E80: Budget Revenue | G80: Actual Revenue | J80: Revenue Variance | K80: Revenue Variance % | M80: Actual Gross Margin %
A81: Packaged Snacks | E81: =SUMIF($C$4:$C$51,A81,$F$4:$F$51) -> 10551210 | G81: =SUMIF($C$4:$C$51,A81,$I$4:$I$51) -> 10554798 | J81: =G81-E81 -> 3587.96 | K81: =IFERROR(J81/E81,"") -> 0.00034005199 | M81: =IFERROR((G81-SUMIF($C$4:$C$51,A81,$P$4:$P$51))/G81,"") -> 0.3776481
A82: Beverages | E82: =SUMIF($C$4:$C$51,A82,$F$4:$F$51) -> 8788091.1 | G82: =SUMIF($C$4:$C$51,A82,$I$4:$I$51) -> 8623347.8 | J82: =G82-E82 -> -164743.3 | K82: =IFERROR(J82/E82,"") -> -0.018746199 | M82: =IFERROR((G82-SUMIF($C$4:$C$51,A82,$P$4:$P$51))/G82,"") -> 0.42543221
A83: Dairy Products | E83: =SUMIF($C$4:$C$51,A83,$F$4:$F$51) -> 10540047 | G83: =SUMIF($C$4:$C$51,A83,$I$4:$I$51) -> 10596560 | J83: =G83-E83 -> 56513.52 | K83: =IFERROR(J83/E83,"") -> 0.0053617904 | M83: =IFERROR((G83-SUMIF($C$4:$C$51,A83,$P$4:$P$51))/G83,"") -> 0.31366836
A84: Bakery Items | E84: =SUMIF($C$4:$C$51,A84,$F$4:$F$51) -> 5805502.1 | G84: =SUMIF($C$4:$C$51,A84,$I$4:$I$51) -> 5785552.4 | J84: =G84-E84 -> -19949.72 | K84: =IFERROR(J84/E84,"") -> -0.003436347 | M84: =IFERROR((G84-SUMIF($C$4:$C$51,A84,$P$4:$P$51))/G84,"") -> 0.3952696

Sheet Expense Budget
A1: EXPENSE BUDGET | Nandini FoodWorks | FY 2024-25 (Budget vs Actual)
A3: Month | B3: Quarter | C3: Expense Category | D3: Type | E3: Budget Expense (Rs.) | F3: Actual Expense (Rs.) | G3: Variance (Rs.) | H3: Variance % | I3: Status
A4: Apr-24 | B4: Q1 | C4: Salaries | D4: Fixed | E4: 285000 | F4: 285170 | G4: =F4-E4 -> 170 | H4: =IFERROR(G4/E4,"") -> 0.00059649123 | I4: =IF(F4>E4*1.02,"Unfavourable",IF(F4<E4*0.98,"Favourable","On Target")) -> On Target
A5: Apr-24 | B5: Q1 | C5: Rent | D5: Fixed | E5: 95000 | F5: 95648 | G5: =F5-E5 -> 648 | H5: =IFERROR(G5/E5,"") -> 0.0068210526 | I5: =IF(F5>E5*1.02,"Unfavourable",IF(F5<E5*0.98,"Favourable","On Target")) -> On Target
A6: Apr-24 | B6: Q1 | C6: Utilities | D6: Variable | E6: 32000 | F6: 31347 | G6: =F6-E6 -> -653 | H6: =IFERROR(G6/E6,"") -> -0.02040625 | I6: =IF(F6>E6*1.02,"Unfavourable",IF(F6<E6*0.98,"Favourable","On Target")) -> Favourable
A7: Apr-24 | B7: Q1 | C7: Marketing | D7: Variable | E7: 55000 | F7: 56590 | G7: =F7-E7 -> 1590 | H7: =IFERROR(G7/E7,"") -> 0.028909091 | I7: =IF(F7>E7*1.02,"Unfavourable",IF(F7<E7*0.98,"Favourable","On Target")) -> Unfavourable
A8: Apr-24 | B8: Q1 | C8: Technology | D8: Fixed | E8: 28000 | F8: 28011 | G8: =F8-E8 -> 11 | H8: =IFERROR(G8/E8,"") -> 0.00039285714 | I8: =IF(F8>E8*1.02,"Unfavourable",IF(F8<E8*0.98,"Favourable","On Target")) -> On Target
A9: Apr-24 | B9: Q1 | C9: Transportation | D9: Variable | E9: 48000 | F9: 46781 | G9: =F9-E9 -> -1219 | H9: =IFERROR(G9/E9,"") -> -0.025395833 | I9: =IF(F9>E9*1.02,"Unfavourable",IF(F9<E9*0.98,"Favourable","On Target")) -> Favourable
A10: Apr-24 | B10: Q1 | C10: Office Expenses | D10: Fixed | E10: 18000 | F10: 18193 | G10: =F10-E10 -> 193 | H10: =IFERROR(G10/E10,"") -> 0.010722222 | I10: =IF(F10>E10*1.02,"Unfavourable",IF(F10<E10*0.98,"Favourable","On Target")) -> On Target
A11: Apr-24 | B11: Q1 | C11: Maintenance | D11: Variable | E11: 15000 | F11: 15429 | G11: =F11-E11 -> 429 | H11: =IFERROR(G11/E11,"") -> 0.0286 | I11: =IF(F11>E11*1.02,"Unfavourable",IF(F11<E11*0.98,"Favourable","On Target")) -> Unfavourable
A12: Apr-24 | B12: Q1 | C12: Other Operating Expenses | D12: Variable | E12: 12000 | F12: 11830 | G12: =F12-E12 -> -170 | H12: =IFERROR(G12/E12,"") -> -0.014166667 | I12: =IF(F12>E12*1.02,"Unfavourable",IF(F12<E12*0.98,"Favourable","On Target")) -> On Target
A13: May-24 | B13: Q1 | C13: Salaries | D13: Fixed | E13: 286710 | F13: 287576 | G13: =F13-E13 -> 866 | H13: =IFERROR(G13/E13,"") -> 0.0030204736 | I13: =IF(F13>E13*1.02,"Unfavourable",IF(F13<E13*0.98,"Favourable","On Target")) -> On Target
A14: May-24 | B14: Q1 | C14: Rent | D14: Fixed | E14: 95570 | F14: 99318 | G14: =F14-E14 -> 3748 | H14: =IFERROR(G14/E14,"") -> 0.039217328 | I14: =IF(F14>E14*1.02,"Unfavourable",IF(F14<E14*0.98,"Favourable","On Target")) -> Unfavourable
A15: May-24 | B15: Q1 | C15: Utilities | D15: Variable | E15: 32192 | F15: 32416 | G15: =F15-E15 -> 224 | H15: =IFERROR(G15/E15,"") -> 0.0069582505 | I15: =IF(F15>E15*1.02,"Unfavourable",IF(F15<E15*0.98,"Favourable","On Target")) -> On Target
... A111: Mar-25 | B111: Q4 | C111: Other Operating Expenses | D111: Variable | E111: 12792 | F111: 13035 | G111: =F111-E111 -> 243 | H111: =IFERROR(G111/E111,"") -> 0.018996248 | I111: =IF(F111>E111*1.02,"Unfavourable",IF(F111<E111*0.98,"Favourable","On Target")) -> On Target
A113: Expense variance logic: Actual > Budget = Unfavourable (cost overrun); Actual < Budget = Favourable (cost saving); within +/-2% = On Target. Status tolerance is a planning convention, not an accounting standard.
A115: Summary by Expense Category (FY 2024-25)
A116: Category | B116: Type | D116: Budget (Rs.) | E116: Actual (Rs.) | F116: Variance (Rs.) | G116: Variance %
A117: Salaries | B117: Fixed | D117: =SUMIF($C$4:$C$111,A117,$E$4:$E$111) -> 3532860 | E117: =SUMIF($C$4:$C$111,A117,$F$4:$F$111) -> 3549486 | F117: =E117-D117 -> 16626 | G117: =IFERROR(F117/D117,"") -> 0.0047061021
A118: Rent | B118: Fixed | D118: =SUMIF($C$4:$C$111,A118,$E$4:$E$111) -> 1177620 | E118: =SUMIF($C$4:$C$111,A118,$F$4:$F$111) -> 1177657 | F118: =E118-D118 -> 37 | G118: =IFERROR(F118/D118,"") -> 3.1419303e-05
A119: Utilities | B119: Variable | D119: =SUMIF($C$4:$C$111,A119,$E$4:$E$111) -> 404651 | E119: =SUMIF($C$4:$C$111,A119,$F$4:$F$111) -> 412209 | F119: =E119-D119 -> 7558 | G119: =IFERROR(F119/D119,"") -> 0.018677824
A120: Marketing | B120: Variable | D120: =SUMIF($C$4:$C$111,A120,$E$4:$E$111) -> 721781 | E120: =SUMIF($C$4:$C$111,A120,$F$4:$F$111) -> 733086 | F120: =E120-D120 -> 11305 | G120: =IFERROR(F120/D120,"") -> 0.015662646
A121: Technology | B121: Fixed | D121: =SUMIF($C$4:$C$111,A121,$E$4:$E$111) -> 347088 | E121: =SUMIF($C$4:$C$111,A121,$F$4:$F$111) -> 350505 | F121: =E121-D121 -> 3417 | G121: =IFERROR(F121/D121,"") -> 0.0098447656
A122: Transportation | B122: Variable | D122: =SUMIF($C$4:$C$111,A122,$E$4:$E$111) -> 606977 | E122: =SUMIF($C$4:$C$111,A122,$F$4:$F$111) -> 610608 | F122: =E122-D122 -> 3631 | G122: =IFERROR(F122/D122,"") -> 0.0059821048
A123: Office Expenses | B123: Fixed | D123: =SUMIF($C$4:$C$111,A123,$E$4:$E$111) -> 223128 | E123: =SUMIF($C$4:$C$111,A123,$F$4:$F$111) -> 227555 | F123: =E123-D123 -> 4427 | G123: =IFERROR(F123/D123,"") -> 0.01984063
A124: Maintenance | B124: Variable | D124: =SUMIF($C$4:$C$111,A124,$E$4:$E$111) -> 185940 | E124: =SUMIF($C$4:$C$111,A124,$F$4:$F$111) -> 185973 | F124: =E124-D124 -> 33 | G124: =IFERROR(F124/D124,"") -> 0.00017747661
A125: Other Operating Expenses | B125: Variable | D125: =SUMIF($C$4:$C$111,A125,$E$4:$E$111) -> 148752 | E125: =SUMIF($C$4:$C$111,A125,$F$4:$F$111) -> 149232 | F125: =E125-D125 -> 480 | G125: =IFERROR(F125/D125,"") -> 0.0032268474
A127: Summary by Cost Type (FY 2024-25)
A128: Type | D128: Budget (Rs.) | E128: Actual (Rs.) | F128: Variance (Rs.) | G128: Variance %
A129: Fixed | D129: =SUMIF($D$4:$D$111,A129,$E$4:$E$111) -> 5280696 | E129: =SUMIF($D$4:$D$111,A129,$F$4:$F$111) -> 5305203 | F129: =E129-D129 -> 24507 | G129: =IFERROR(F129/D129,"") -> 0.0046408655
A130: Variable | D130: =SUMIF($D$4:$D$111,A130,$E$4:$E$111) -> 2068101 | E130: =SUMIF($D$4:$D$111,A130,$F$4:$F$111) -> 2091108 | F130: =E130-D130 -> 23007 | G130: =IFERROR(F130/D130,"") -> 0.011124698
A133: Forecast Expense (Apr-25 to Sep-25) - trend-based, see Financial Forecast sheet for method
A134: Month | B134: Quarter | C134: Expense Category | D134: Type | F134: Forecast Expense (Rs.)
A135: Apr-25 | B135: Q1 | C135: Salaries | D135: Fixed | F135: 308030
A136: Apr-25 | B136: Q1 | C136: Rent | D136: Fixed | F136: 103040.05
A137: Apr-25 | B137: Q1 | C137: Utilities | D137: Variable | F137: 33552.17
A138: Apr-25 | B138: Q1 | C138: Marketing | D138: Variable | F138: 61064.99
A139: Apr-25 | B139: Q1 | C139: Technology | D139: Fixed | F139: 29978.6
A140: Apr-25 | B140: Q1 | C140: Transportation | D140: Variable | F140: 49859.85
A141: Apr-25 | B141: Q1 | C141: Office Expenses | D141: Fixed | F141: 20022.08
A142: Apr-25 | B142: Q1 | C142: Maintenance | D142: Variable | F142: 15220.69
A143: Apr-25 | B143: Q1 | C143: Other Operating Expenses | D143: Variable | F143: 13161.14
A144: May-25 | B144: Q1 | C144: Salaries | D144: Fixed | F144: 310018.76
A145: May-25 | B145: Q1 | C145: Rent | D145: Fixed | F145: 103762.13
A146: May-25 | B146: Q1 | C146: Utilities | D146: Variable | F146: 33834.69
... A188: Sep-25 | B188: Q2 | C188: Other Operating Expenses | D188: Variable | F188: 13810.38

Sheet Budget vs Actual
A1: BUDGET vs ACTUAL | Monthly Revenue, Expense & Net Profit | FY 2024-25
A3: Month | B3: Quarter | C3: Budget Revenue | D3: Actual Revenue | E3: Revenue Variance | F3: Revenue Var % | G3: Revenue Status | H3: Budget Expense (incl. COGS) | I3: Actual Expense (incl. COGS) | J3: Expense Variance | K3: Expense Var % | L3: Expense Status | M3: Budget Net Profit | N3: Actual Net Profit | O3: Profit Variance | P3: Profit Var % | Q3: Profit Status
A4: Apr-24 | B4: Q1 | C4: =SUMIF('Revenue Planning'!$A$4:$A$51,A4,'Revenue Planning'!$F$4:$F$51) -> 2861000 | D4: =SUMIF('Revenue Planning'!$A$4:$A$51,A4,'Revenue Planning'!$I$4:$I$51) -> 2874061.9 | E4: =D4-C4 -> 13061.94 | F4: =IFERROR(E4/C4,"") -> 0.0045655156 | G4: =IF(D4>=C4*0.99,"Favourable","Unfavourable") -> Favourable | H4: =SUMIF('Expense Budget'!$A$4:$A$111,A4,'Expense Budget'!$E$4:$E$111)+SUMIF('Revenue Planning'!$A$4:$A$51,A4,'Revenue Planning'!$N$4:$N$51) -> 2371400 | I4: =SUMIF('Expense Budget'!$A$4:$A$111,A4,'Expense Budget'!$F$4:$F$111)+SUMIF('Revenue Planning'!$A$4:$A$51,A4,'Revenue Planning'!$P$4:$P$51) -> 2371148.5 | J4: =I4-H4 -> -251.50729 | K4: =IFERROR(J4/H4,"") -> -0.00010605857 | L4: =IF(I4<=H4*1.01,"Favourable","Unfavourable") -> Favourable | M4: =C4-H4 -> 489600 | N4: =D4-I4 -> 502913.45 | O4: =N4-M4 -> 13313.447 | P4: =IFERROR(O4/M4,"") -> 0.027192499 | Q4: =IF(N4>=M4*0.99,"Favourable","Unfavourable") -> Favourable
A5: May-24 | B5: Q1 | C5: =SUMIF('Revenue Planning'!$A$4:$A$51,A5,'Revenue Planning'!$F$4:$F$51) -> 2978440.7 | D5: =SUMIF('Revenue Planning'!$A$4:$A$51,A5,'Revenue Planning'!$I$4:$I$51) -> 2956844.2 | E5: =D5-C5 -> -21596.51 | F5: =IFERROR(E5/C5,"") -> -0.0072509451 | G5: =IF(D5>=C5*0.99,"Favourable","Unfavourable") -> Favourable | H5: =SUMIF('Expense Budget'!$A$4:$A$111,A5,'Expense Budget'!$E$4:$E$111)+SUMIF('Revenue Planning'!$A$4:$A$51,A5,'Revenue Planning'!$N$4:$N$51) -> 2446171.9 | I5: =SUMIF('Expense Budget'!$A$4:$A$111,A5,'Expense Budget'!$F$4:$F$111)+SUMIF('Revenue Planning'!$A$4:$A$51,A5,'Revenue Planning'!$P$4:$P$51) -> 2437711.1 | J5: =I5-H5 -> -8460.8037 | K5: =IFERROR(J5/H5,"") -> -0.0034587936 | L5: =IF(I5<=H5*1.01,"Favourable","Unfavourable") -> Favourable | M5: =C5-H5 -> 532268.8 | N5: =D5-I5 -> 519133.09 | O5: =N5-M5 -> -13135.706 | P5: =IFERROR(O5/M5,"") -> -0.024678708 | Q5: =IF(N5>=M5*0.99,"Favourable","Unfavourable") -> Unfavourable
A6: Jun-24 | B6: Q1 | C6: =SUMIF('Revenue Planning'!$A$4:$A$51,A6,'Revenue Planning'!$F$4:$F$51) -> 2943903.8 | D6: =SUMIF('Revenue Planning'!$A$4:$A$51,A6,'Revenue Planning'!$I$4:$I$51) -> 2920238.2 | E6: =D6-C6 -> -23665.52 | F6: =IFERROR(E6/C6,"") -> -0.0080388226 | G6: =IF(D6>=C6*0.99,"Favourable","Unfavourable") -> Favourable | H6: =SUMIF('Expense Budget'!$A$4:$A$111,A6,'Expense Budget'!$E$4:$E$111)+SUMIF('Revenue Planning'!$A$4:$A$51,A6,'Revenue Planning'!$N$4:$N$51) -> 2429053.6 | I6: =SUMIF('Expense Budget'!$A$4:$A$111,A6,'Expense Budget'!$F$4:$F$111)+SUMIF('Revenue Planning'!$A$4:$A$51,A6,'Revenue Planning'!$P$4:$P$51) -> 2447489 | J6: =I6-H6 -> 18435.404 | K6: =IFERROR(J6/H6,"") -> 0.007589542 | L6: =IF(I6<=H6*1.01,"Favourable","Unfavourable") -> Favourable | M6: =C6-H6 -> 514850.2 | N6: =D6-I6 -> 472749.28 | O6: =N6-M6 -> -42100.924 | P6: =IFERROR(O6/M6,"") -> -0.081773152 | Q6: =IF(N6>=M6*0.99,"Favourable","Unfavourable") -> Unfavourable
A7: Jul-24 | B7: Q2 | C7: =SUMIF('Revenue Planning'!$A$4:$A$51,A7,'Revenue Planning'!$F$4:$F$51) -> 2742367 | D7: =SUMIF('Revenue Planning'!$A$4:$A$51,A7,'Revenue Planning'!$I$4:$I$51) -> 2661268.9 | E7: =D7-C7 -> -81098.12 | F7: =IFERROR(E7/C7,"") -> -0.029572308 | G7: =IF(D7>=C7*0.99,"Favourable","Unfavourable") -> Unfavourable | H7: =SUMIF('Expense Budget'!$A$4:$A$111,A7,'Expense Budget'!$E$4:$E$111)+SUMIF('Revenue Planning'!$A$4:$A$51,A7,'Revenue Planning'!$N$4:$N$51) -> 2312882.6 | I7: =SUMIF('Expense Budget'!$A$4:$A$111,A7,'Expense Budget'!$F$4:$F$111)+SUMIF('Revenue Planning'!$A$4:$A$51,A7,'Revenue Planning'!$P$4:$P$51) -> 2300692 | J7: =I7-H7 -> -12190.533 | K7: =IFERROR(J7/H7,"") -> -0.00527071 | L7: =IF(I7<=H7*1.01,"Favourable","Unfavourable") -> Favourable | M7: =C7-H7 -> 429484.43 | N7: =D7-I7 -> 360576.85 | O7: =N7-M7 -> -68907.587 | P7: =IFERROR(O7/M7,"") -> -0.16044257 | Q7: =IF(N7>=M7*0.99,"Favourable","Unfavourable") -> Unfavourable
A8: Aug-24 | B8: Q2 | C8: =SUMIF('Revenue Planning'!$A$4:$A$51,A8,'Revenue Planning'!$F$4:$F$51) -> 2743148.7 | D8: =SUMIF('Revenue Planning'!$A$4:$A$51,A8,'Revenue Planning'!$I$4:$I$51) -> 2611563.2 | E8: =D8-C8 -> -131585.54 | F8: =IFERROR(E8/C8,"") -> -0.047968796 | G8: =IF(D8>=C8*0.99,"Favourable","Unfavourable") -> Unfavourable | H8: =SUMIF('Expense Budget'!$A$4:$A$111,A8,'Expense Budget'!$E$4:$E$111)+SUMIF('Revenue Planning'!$A$4:$A$51,A8,'Revenue Planning'!$N$4:$N$51) -> 2317691.4 | I8: =SUMIF('Expense Budget'!$A$4:$A$111,A8,'Expense Budget'!$F$4:$F$111)+SUMIF('Revenue Planning'!$A$4:$A$51,A8,'Revenue Planning'!$P$4:$P$51) -> 2282909.8 | J8: =I8-H8 -> -34781.598 | K8: =IFERROR(J8/H8,"") -> -0.015007002 | L8: =IF(I8<=H8*1.01,"Favourable","Unfavourable") -> Favourable | M8: =C8-H8 -> 425457.33 | N8: =D8-I8 -> 328653.39 | O8: =N8-M8 -> -96803.942 | P8: =IFERROR(O8/M8,"") -> -0.22752914 | Q8: =IF(N8>=M8*0.99,"Favourable","Unfavourable") -> Unfavourable
A9: Sep-24 | B9: Q2 | C9: =SUMIF('Revenue Planning'!$A$4:$A$51,A9,'Revenue Planning'!$F$4:$F$51) -> 2843333.8 | D9: =SUMIF('Revenue Planning'!$A$4:$A$51,A9,'Revenue Planning'!$I$4:$I$51) -> 2826123.7 | E9: =D9-C9 -> -17210.14 | F9: =IFERROR(E9/C9,"") -> -0.0060528032 | G9: =IF(D9>=C9*0.99,"Favourable","Unfavourable") -> Favourable | H9: =SUMIF('Expense Budget'!$A$4:$A$111,A9,'Expense Budget'!$E$4:$E$111)+SUMIF('Revenue Planning'!$A$4:$A$51,A9,'Revenue Planning'!$N$4:$N$51) -> 2383317.2 | I9: =SUMIF('Expense Budget'!$A$4:$A$111,A9,'Expense Budget'!$F$4:$F$111)+SUMIF('Revenue Planning'!$A$4:$A$51,A9,'Revenue Planning'!$P$4:$P$51) -> 2364068.3 | J9: =I9-H9 -> -19248.973 | K9: =IFERROR(J9/H9,"") -> -0.0080765467 | L9: =IF(I9<=H9*1.01,"Favourable","Unfavourable") -> Favourable | M9: =C9-H9 -> 460016.58 | N9: =D9-I9 -> 462055.41 | O9: =N9-M9 -> 2038.8331 | P9: =IFERROR(O9/M9,"") -> 0.0044320861 | Q9: =IF(N9>=M9*0.99,"Favourable","Unfavourable") -> Favourable
A10: Oct-24 | B10: Q3 | C10: =SUMIF('Revenue Planning'!$A$4:$A$51,A10,'Revenue Planning'!$F$4:$F$51) -> 3308101.5 | D10: =SUMIF('Revenue Planning'!$A$4:$A$51,A10,'Revenue Planning'!$I$4:$I$51) -> 3579618.2 | E10: =D10-C10 -> 271516.74 | F10: =IFERROR(E10/C10,"") -> 0.082076303 | G10: =IF(D10>=C10*0.99,"Favourable","Unfavourable") -> Favourable | H10: =SUMIF('Expense Budget'!$A$4:$A$111,A10,'Expense Budget'!$E$4:$E$111)+SUMIF('Revenue Planning'!$A$4:$A$51,A10,'Revenue Planning'!$N$4:$N$51) -> 2705340.5 | I10: =SUMIF('Expense Budget'!$A$4:$A$111,A10,'Expense Budget'!$F$4:$F$111)+SUMIF('Revenue Planning'!$A$4:$A$51,A10,'Revenue Planning'!$P$4:$P$51) -> 2869470.4 | J10: =I10-H10 -> 164129.81 | K10: =IFERROR(J10/H10,"") -> 0.060668817 | L10: =IF(I10<=H10*1.01,"Favourable","Unfavourable") -> Unfavourable | M10: =C10-H10 -> 602760.95 | N10: =D10-I10 -> 710147.88 | O10: =N10-M10 -> 107386.93 | P10: =IFERROR(O10/M10,"") -> 0.1781584 | Q10: =IF(N10>=M10*0.99,"Favourable","Unfavourable") -> Favourable
A11: Nov-24 | B11: Q3 | C11: =SUMIF('Revenue Planning'!$A$4:$A$51,A11,'Revenue Planning'!$F$4:$F$51) -> 3456789.7 | D11: =SUMIF('Revenue Planning'!$A$4:$A$51,A11,'Revenue Planning'!$I$4:$I$51) -> 3669694.4 | E11: =D11-C11 -> 212904.72 | F11: =IFERROR(E11/C11,"") -> 0.061590302 | G11: =IF(D11>=C11*0.99,"Favourable","Unfavourable") -> Favourable | H11: =SUMIF('Expense Budget'!$A$4:$A$111,A11,'Expense Budget'!$E$4:$E$111)+SUMIF('Revenue Planning'!$A$4:$A$51,A11,'Revenue Planning'!$N$4:$N$51) -> 2804484.3 | I11: =SUMIF('Expense Budget'!$A$4:$A$111,A11,'Expense Budget'!$F$4:$F$111)+SUMIF('Revenue Planning'!$A$4:$A$51,A11,'Revenue Planning'!$P$4:$P$51) -> 2932697 | J11: =I11-H11 -> 128212.63 | K11: =IFERROR(J11/H11,"") -> 0.045717006 | L11: =IF(I11<=H11*1.01,"Favourable","Unfavourable") -> Unfavourable | M11: =C11-H11 -> 652305.33 | N11: =D11-I11 -> 736997.43 | O11: =N11-M11 -> 84692.092 | P11: =IFERROR(O11/M11,"") -> 0.12983504 | Q11: =IF(N11>=M11*0.99,"Favourable","Unfavourable") -> Favourable
A12: Dec-24 | B12: Q3 | C12: =SUMIF('Revenue Planning'!$A$4:$A$51,A12,'Revenue Planning'!$F$4:$F$51) -> 3144592.9 | D12: =SUMIF('Revenue Planning'!$A$4:$A$51,A12,'Revenue Planning'!$I$4:$I$51) -> 3131491 | E12: =D12-C12 -> -13101.9 | F12: =IFERROR(E12/C12,"") -> -0.0041664853 | G12: =IF(D12>=C12*0.99,"Favourable","Unfavourable") -> Favourable | H12: =SUMIF('Expense Budget'!$A$4:$A$111,A12,'Expense Budget'!$E$4:$E$111)+SUMIF('Revenue Planning'!$A$4:$A$51,A12,'Revenue Planning'!$N$4:$N$51) -> 2581234.8 | I12: =SUMIF('Expense Budget'!$A$4:$A$111,A12,'Expense Budget'!$F$4:$F$111)+SUMIF('Revenue Planning'!$A$4:$A$51,A12,'Revenue Planning'!$P$4:$P$51) -> 2563750 | J12: =I12-H12 -> -17484.814 | K12: =IFERROR(J12/H12,"") -> -0.0067738176 | L12: =IF(I12<=H12*1.01,"Favourable","Unfavourable") -> Favourable | M12: =C12-H12 -> 563358.06 | N12: =D12-I12 -> 567740.97 | O12: =N12-M12 -> 4382.9138 | P12: =IFERROR(O12/M12,"") -> 0.0077799789 | Q12: =IF(N12>=M12*0.99,"Favourable","Unfavourable") -> Favourable
A13: Jan-25 | B13: Q4 | C13: =SUMIF('Revenue Planning'!$A$4:$A$51,A13,'Revenue Planning'!$F$4:$F$51) -> 2770198.7 | D13: =SUMIF('Revenue Planning'!$A$4:$A$51,A13,'Revenue Planning'!$I$4:$I$51) -> 2469819.4 | E13: =D13-C13 -> -300379.31 | F13: =IFERROR(E13/C13,"") -> -0.10843241 | G13: =IF(D13>=C13*0.99,"Favourable","Unfavourable") -> Unfavourable | H13: =SUMIF('Expense Budget'!$A$4:$A$111,A13,'Expense Budget'!$E$4:$E$111)+SUMIF('Revenue Planning'!$A$4:$A$51,A13,'Revenue Planning'!$N$4:$N$51) -> 2354496.4 | I13: =SUMIF('Expense Budget'!$A$4:$A$111,A13,'Expense Budget'!$F$4:$F$111)+SUMIF('Revenue Planning'!$A$4:$A$51,A13,'Revenue Planning'!$P$4:$P$51) -> 2206679.6 | J13: =I13-H13 -> -147816.79 | K13: =IFERROR(J13/H13,"") -> -0.062780639 | L13: =IF(I13<=H13*1.01,"Favourable","Unfavourable") -> Favourable | M13: =C13-H13 -> 415702.25 | N13: =D13-I13 -> 263139.73 | O13: =N13-M13 -> -152562.52 | P13: =IFERROR(O13/M13,"") -> -0.3669995 | Q13: =IF(N13>=M13*0.99,"Favourable","Unfavourable") -> Unfavourable
A14: Feb-25 | B14: Q4 | C14: =SUMIF('Revenue Planning'!$A$4:$A$51,A14,'Revenue Planning'!$F$4:$F$51) -> 2836900.5 | D14: =SUMIF('Revenue Planning'!$A$4:$A$51,A14,'Revenue Planning'!$I$4:$I$51) -> 2830605.6 | E14: =D14-C14 -> -6294.88 | F14: =IFERROR(E14/C14,"") -> -0.0022189287 | G14: =IF(D14>=C14*0.99,"Favourable","Unfavourable") -> Favourable | H14: =SUMIF('Expense Budget'!$A$4:$A$111,A14,'Expense Budget'!$E$4:$E$111)+SUMIF('Revenue Planning'!$A$4:$A$51,A14,'Revenue Planning'!$N$4:$N$51) -> 2397655.3 | I14: =SUMIF('Expense Budget'!$A$4:$A$111,A14,'Expense Budget'!$F$4:$F$111)+SUMIF('Revenue Planning'!$A$4:$A$51,A14,'Revenue Planning'!$P$4:$P$51) -> 2390328.8 | J14: =I14-H14 -> -7326.46 | K14: =IFERROR(J14/H14,"") -> -0.003055677 | L14: =IF(I14<=H14*1.01,"Favourable","Unfavourable") -> Favourable | M14: =C14-H14 -> 439245.23 | N14: =D14-I14 -> 440276.81 | O14: =N14-M14 -> 1031.58 | P14: =IFERROR(O14/M14,"") -> 0.0023485287 | Q14: =IF(N14>=M14*0.99,"Favourable","Unfavourable") -> Favourable
A15: Mar-25 | B15: Q4 | C15: =SUMIF('Revenue Planning'!$A$4:$A$51,A15,'Revenue Planning'!$F$4:$F$51) -> 3056072.8 | D15: =SUMIF('Revenue Planning'!$A$4:$A$51,A15,'Revenue Planning'!$I$4:$I$51) -> 3028929.7 | E15: =D15-C15 -> -27143.02 | F15: =IFERROR(E15/C15,"") -> -0.0088816668 | G15: =IF(D15>=C15*0.99,"Favourable","Unfavourable") -> Favourable | H15: =SUMIF('Expense Budget'!$A$4:$A$111,A15,'Expense Budget'!$E$4:$E$111)+SUMIF('Revenue Planning'!$A$4:$A$51,A15,'Revenue Planning'!$N$4:$N$51) -> 2534445.1 | I15: =SUMIF('Expense Budget'!$A$4:$A$111,A15,'Expense Budget'!$F$4:$F$111)+SUMIF('Revenue Planning'!$A$4:$A$51,A15,'Revenue Planning'!$P$4:$P$51) -> 2524317 | J15: =I15-H15 -> -10128.076 | K15: =IFERROR(J15/H15,"") -> -0.0039961712 | L15: =IF(I15<=H15*1.01,"Favourable","Unfavourable") -> Favourable | M15: =C15-H15 -> 521627.7 | N15: =D15-I15 -> 504612.76 | O15: =N15-M15 -> -17014.944 | P15: =IFERROR(O15/M15,"") -> -0.032618942 | Q15: =IF(N15>=M15*0.99,"Favourable","Unfavourable") -> Unfavourable
A16: FY 2024-25 Total | C16: =SUM(C4:C15) -> 35684850 | D16: =SUM(D4:D15) -> 35560258 | E16: =SUM(E4:E15) -> -124591.54 | F16: =IFERROR(E16/C16,"") -> -0.0034914408 | H16: =SUM(H4:H15) -> 29638173 | I16: =SUM(I4:I15) -> 29691261 | J16: =SUM(J4:J15) -> 53088.287 | K16: =IFERROR(J16/H16,"") -> 0.0017912132 | M16: =SUM(M4:M15) -> 6046676.9 | N16: =SUM(N4:N15) -> 5868997 | O16: =SUM(O4:O15) -> -177679.83 | P16: =IFERROR(O16/M16,"") -> -0.029384707
A18: Expense figures here include Cost of Goods Sold (COGS) from the Revenue Planning sheet plus all operating expenses from the Expense Budget sheet, so Net Profit = Revenue - COGS - Operating Expenses.

Sheet Variance Analysis
A1: VARIANCE ANALYSIS | Revenue Volume/Price Decomposition & Profit Variance Drivers | FY 2024-25
A3: Month | B3: Revenue Budget | C3: Revenue Actual | D3: Revenue Variance | E3: Revenue Var % | F3: Volume Variance (Rs.) | G3: Price Variance (Rs.) | H3: Expense Budget | I3: Expense Actual | J3: Expense Variance | K3: Expense Var % | L3: Profit Budget | M3: Profit Actual | N3: Profit Variance | O3: Profit Var % | P3: Status | Q3: Likely Driver
A4: Apr-24 | B4: ='Budget vs Actual'!C4 -> 2861000 | C4: ='Budget vs Actual'!D4 -> 2874061.9 | D4: =C4-B4 -> 13061.94 | E4: =IFERROR(D4/B4,"") -> 0.0045655156 | F4: =SUMPRODUCT(('Revenue Planning'!$A$4:$A$51=A4)*('Revenue Planning'!$G$4:$G$51-'Revenue Planning'!$D$4:$D$51)*'Revenue Planning'!$E$4:$E$51) -> 15083 | G4: =SUMPRODUCT(('Revenue Planning'!$A$4:$A$51=A4)*('Revenue Planning'!$H$4:$H$51-'Revenue Planning'!$E$4:$E$51)*'Revenue Planning'!$G$4:$G$51) -> -2021.06 | H4: ='Budget vs Actual'!H4 -> 2371400 | I4: ='Budget vs Actual'!I4 -> 2371148.5 | J4: =I4-H4 -> -251.50729 | K4: =IFERROR(J4/H4,"") -> -0.00010605857 | L4: ='Budget vs Actual'!M4 -> 489600 | M4: ='Budget vs Actual'!N4 -> 502913.45 | N4: =M4-L4 -> 13313.447 | O4: =IFERROR(N4/L4,"") -> 0.027192499 | P4: =IF(N4>=0,"Favourable","Unfavourable") -> Favourable | Q4: =IF(AND(ABS(F4)>=ABS(G4),ABS(F4)>=ABS(J4)),"Sales Volume",IF(AND(ABS(G4)>ABS(F4),ABS(G4)>=ABS(J4)),"Selling Price","Operating Cost")) -> Sales Volume
A5: May-24 | B5: ='Budget vs Actual'!C5 -> 2978440.7 | C5: ='Budget vs Actual'!D5 -> 2956844.2 | D5: =C5-B5 -> -21596.51 | E5: =IFERROR(D5/B5,"") -> -0.0072509451 | F5: =SUMPRODUCT(('Revenue Planning'!$A$4:$A$51=A5)*('Revenue Planning'!$G$4:$G$51-'Revenue Planning'!$D$4:$D$51)*'Revenue Planning'!$E$4:$E$51) -> -26115.69 | G5: =SUMPRODUCT(('Revenue Planning'!$A$4:$A$51=A5)*('Revenue Planning'!$H$4:$H$51-'Revenue Planning'!$E$4:$E$51)*'Revenue Planning'!$G$4:$G$51) -> 4519.18 | H5: ='Budget vs Actual'!H5 -> 2446171.9 | I5: ='Budget vs Actual'!I5 -> 2437711.1 | J5: =I5-H5 -> -8460.8037 | K5: =IFERROR(J5/H5,"") -> -0.0034587936 | L5: ='Budget vs Actual'!M5 -> 532268.8 | M5: ='Budget vs Actual'!N5 -> 519133.09 | N5: =M5-L5 -> -13135.706 | O5: =IFERROR(N5/L5,"") -> -0.024678708 | P5: =IF(N5>=0,"Favourable","Unfavourable") -> Unfavourable | Q5: =IF(AND(ABS(F5)>=ABS(G5),ABS(F5)>=ABS(J5)),"Sales Volume",IF(AND(ABS(G5)>ABS(F5),ABS(G5)>=ABS(J5)),"Selling Price","Operating Cost")) -> Sales Volume
A6: Jun-24 | B6: ='Budget vs Actual'!C6 -> 2943903.8 | C6: ='Budget vs Actual'!D6 -> 2920238.2 | D6: =C6-B6 -> -23665.52 | E6: =IFERROR(D6/B6,"") -> -0.0080388226 | F6: =SUMPRODUCT(('Revenue Planning'!$A$4:$A$51=A6)*('Revenue Planning'!$G$4:$G$51-'Revenue Planning'!$D$4:$D$51)*'Revenue Planning'!$E$4:$E$51) -> -15001.52 | G6: =SUMPRODUCT(('Revenue Planning'!$A$4:$A$51=A6)*('Revenue Planning'!$H$4:$H$51-'Revenue Planning'!$E$4:$E$51)*'Revenue Planning'!$G$4:$G$51) -> -8664 | H6: ='Budget vs Actual'!H6 -> 2429053.6 | I6: ='Budget vs Actual'!I6 -> 2447489 | J6: =I6-H6 -> 18435.404 | K6: =IFERROR(J6/H6,"") -> 0.007589542 | L6: ='Budget vs Actual'!M6 -> 514850.2 | M6: ='Budget vs Actual'!N6 -> 472749.28 | N6: =M6-L6 -> -42100.924 | O6: =IFERROR(N6/L6,"") -> -0.081773152 | P6: =IF(N6>=0,"Favourable","Unfavourable") -> Unfavourable | Q6: =IF(AND(ABS(F6)>=ABS(G6),ABS(F6)>=ABS(J6)),"Sales Volume",IF(AND(ABS(G6)>ABS(F6),ABS(G6)>=ABS(J6)),"Selling Price","Operating Cost")) -> Operating Cost
A7: Jul-24 | B7: ='Budget vs Actual'!C7 -> 2742367 | C7: ='Budget vs Actual'!D7 -> 2661268.9 | D7: =C7-B7 -> -81098.12 | E7: =IFERROR(D7/B7,"") -> -0.029572308 | F7: =SUMPRODUCT(('Revenue Planning'!$A$4:$A$51=A7)*('Revenue Planning'!$G$4:$G$51-'Revenue Planning'!$D$4:$D$51)*'Revenue Planning'!$E$4:$E$51) -> -78559.74 | G7: =SUMPRODUCT(('Revenue Planning'!$A$4:$A$51=A7)*('Revenue Planning'!$H$4:$H$51-'Revenue Planning'!$E$4:$E$51)*'Revenue Planning'!$G$4:$G$51) -> -2538.38 | H7: ='Budget vs Actual'!H7 -> 2312882.6 | I7: ='Budget vs Actual'!I7 -> 2300692 | J7: =I7-H7 -> -12190.533 | K7: =IFERROR(J7/H7,"") -> -0.00527071 | L7: ='Budget vs Actual'!M7 -> 429484.43 | M7: ='Budget vs Actual'!N7 -> 360576.85 | N7: =M7-L7 -> -68907.587 | O7: =IFERROR(N7/L7,"") -> -0.16044257 | P7: =IF(N7>=0,"Favourable","Unfavourable") -> Unfavourable | Q7: =IF(AND(ABS(F7)>=ABS(G7),ABS(F7)>=ABS(J7)),"Sales Volume",IF(AND(ABS(G7)>ABS(F7),ABS(G7)>=ABS(J7)),"Selling Price","Operating Cost")) -> Sales Volume
A8: Aug-24 | B8: ='Budget vs Actual'!C8 -> 2743148.7 | C8: ='Budget vs Actual'!D8 -> 2611563.2 | D8: =C8-B8 -> -131585.54 | E8: =IFERROR(D8/B8,"") -> -0.047968796 | F8: =SUMPRODUCT(('Revenue Planning'!$A$4:$A$51=A8)*('Revenue Planning'!$G$4:$G$51-'Revenue Planning'!$D$4:$D$51)*'Revenue Planning'!$E$4:$E$51) -> -116531.22 | G8: =SUMPRODUCT(('Revenue Planning'!$A$4:$A$51=A8)*('Revenue Planning'!$H$4:$H$51-'Revenue Planning'!$E$4:$E$51)*'Revenue Planning'!$G$4:$G$51) -> -15054.32 | H8: ='Budget vs Actual'!H8 -> 2317691.4 | I8: ='Budget vs Actual'!I8 -> 2282909.8 | J8: =I8-H8 -> -34781.598 | K8: =IFERROR(J8/H8,"") -> -0.015007002 | L8: ='Budget vs Actual'!M8 -> 425457.33 | M8: ='Budget vs Actual'!N8 -> 328653.39 | N8: =M8-L8 -> -96803.942 | O8: =IFERROR(N8/L8,"") -> -0.22752914 | P8: =IF(N8>=0,"Favourable","Unfavourable") -> Unfavourable | Q8: =IF(AND(ABS(F8)>=ABS(G8),ABS(F8)>=ABS(J8)),"Sales Volume",IF(AND(ABS(G8)>ABS(F8),ABS(G8)>=ABS(J8)),"Selling Price","Operating Cost")) -> Sales Volume
A9: Sep-24 | B9: ='Budget vs Actual'!C9 -> 2843333.8 | C9: ='Budget vs Actual'!D9 -> 2826123.7 | D9: =C9-B9 -> -17210.14 | E9: =IFERROR(D9/B9,"") -> -0.0060528032 | F9: =SUMPRODUCT(('Revenue Planning'!$A$4:$A$51=A9)*('Revenue Planning'!$G$4:$G$51-'Revenue Planning'!$D$4:$D$51)*'Revenue Planning'!$E$4:$E$51) -> -12101.82 | G9: =SUMPRODUCT(('Revenue Planning'!$A$4:$A$51=A9)*('Revenue Planning'!$H$4:$H$51-'Revenue Planning'!$E$4:$E$51)*'Revenue Planning'!$G$4:$G$51) -> -5108.32 | H9: ='Budget vs Actual'!H9 -> 2383317.2 | I9: ='Budget vs Actual'!I9 -> 2364068.3 | J9: =I9-H9 -> -19248.973 | K9: =IFERROR(J9/H9,"") -> -0.0080765467 | L9: ='Budget vs Actual'!M9 -> 460016.58 | M9: ='Budget vs Actual'!N9 -> 462055.41 | N9: =M9-L9 -> 2038.8331 | O9: =IFERROR(N9/L9,"") -> 0.0044320861 | P9: =IF(N9>=0,"Favourable","Unfavourable") -> Favourable | Q9: =IF(AND(ABS(F9)>=ABS(G9),ABS(F9)>=ABS(J9)),"Sales Volume",IF(AND(ABS(G9)>ABS(F9),ABS(G9)>=ABS(J9)),"Selling Price","Operating Cost")) -> Operating Cost
A10: Oct-24 | B10: ='Budget vs Actual'!C10 -> 3308101.5 | C10: ='Budget vs Actual'!D10 -> 3579618.2 | D10: =C10-B10 -> 271516.74 | E10: =IFERROR(D10/B10,"") -> 0.082076303 | F10: =SUMPRODUCT(('Revenue Planning'!$A$4:$A$51=A10)*('Revenue Planning'!$G$4:$G$51-'Revenue Planning'!$D$4:$D$51)*'Revenue Planning'!$E$4:$E$51) -> 236075.88 | G10: =SUMPRODUCT(('Revenue Planning'!$A$4:$A$51=A10)*('Revenue Planning'!$H$4:$H$51-'Revenue Planning'!$E$4:$E$51)*'Revenue Planning'!$G$4:$G$51) -> 35440.86 | H10: ='Budget vs Actual'!H10 -> 2705340.5 | I10: ='Budget vs Actual'!I10 -> 2869470.4 | J10: =I10-H10 -> 164129.81 | K10: =IFERROR(J10/H10,"") -> 0.060668817 | L10: ='Budget vs Actual'!M10 -> 602760.95 | M10: ='Budget vs Actual'!N10 -> 710147.88 | N10: =M10-L10 -> 107386.93 | O10: =IFERROR(N10/L10,"") -> 0.1781584 | P10: =IF(N10>=0,"Favourable","Unfavourable") -> Favourable | Q10: =IF(AND(ABS(F10)>=ABS(G10),ABS(F10)>=ABS(J10)),"Sales Volume",IF(AND(ABS(G10)>ABS(F10),ABS(G10)>=ABS(J10)),"Selling Price","Operating Cost")) -> Sales Volume
A11: Nov-24 | B11: ='Budget vs Actual'!C11 -> 3456789.7 | C11: ='Budget vs Actual'!D11 -> 3669694.4 | D11: =C11-B11 -> 212904.72 | E11: =IFERROR(D11/B11,"") -> 0.061590302 | F11: =SUMPRODUCT(('Revenue Planning'!$A$4:$A$51=A11)*('Revenue Planning'!$G$4:$G$51-'Revenue Planning'!$D$4:$D$51)*'Revenue Planning'!$E$4:$E$51) -> 176465.51 | G11: =SUMPRODUCT(('Revenue Planning'!$A$4:$A$51=A11)*('Revenue Planning'!$H$4:$H$51-'Revenue Planning'!$E$4:$E$51)*'Revenue Planning'!$G$4:$G$51) -> 36439.21 | H11: ='Budget vs Actual'!H11 -> 2804484.3 | I11: ='Budget vs Actual'!I11 -> 2932697 | J11: =I11-H11 -> 128212.63 | K11: =IFERROR(J11/H11,"") -> 0.045717006 | L11: ='Budget vs Actual'!M11 -> 652305.33 | M11: ='Budget vs Actual'!N11 -> 736997.43 | N11: =M11-L11 -> 84692.092 | O11: =IFERROR(N11/L11,"") -> 0.12983504 | P11: =IF(N11>=0,"Favourable","Unfavourable") -> Favourable | Q11: =IF(AND(ABS(F11)>=ABS(G11),ABS(F11)>=ABS(J11)),"Sales Volume",IF(AND(ABS(G11)>ABS(F11),ABS(G11)>=ABS(J11)),"Selling Price","Operating Cost")) -> Sales Volume
A12: Dec-24 | B12: ='Budget vs Actual'!C12 -> 3144592.9 | C12: ='Budget vs Actual'!D12 -> 3131491 | D12: =C12-B12 -> -13101.9 | E12: =IFERROR(D12/B12,"") -> -0.0041664853 | F12: =SUMPRODUCT(('Revenue Planning'!$A$4:$A$51=A12)*('Revenue Planning'!$G$4:$G$51-'Revenue Planning'!$D$4:$D$51)*'Revenue Planning'!$E$4:$E$51) -> -9911.19 | G12: =SUMPRODUCT(('Revenue Planning'!$A$4:$A$51=A12)*('Revenue Planning'!$H$4:$H$51-'Revenue Planning'!$E$4:$E$51)*'Revenue Planning'!$G$4:$G$51) -> -3190.71 | H12: ='Budget vs Actual'!H12 -> 2581234.8 | I12: ='Budget vs Actual'!I12 -> 2563750 | J12: =I12-H12 -> -17484.814 | K12: =IFERROR(J12/H12,"") -> -0.0067738176 | L12: ='Budget vs Actual'!M12 -> 563358.06 | M12: ='Budget vs Actual'!N12 -> 567740.97 | N12: =M12-L12 -> 4382.9138 | O12: =IFERROR(N12/L12,"") -> 0.0077799789 | P12: =IF(N12>=0,"Favourable","Unfavourable") -> Favourable | Q12: =IF(AND(ABS(F12)>=ABS(G12),ABS(F12)>=ABS(J12)),"Sales Volume",IF(AND(ABS(G12)>ABS(F12),ABS(G12)>=ABS(J12)),"Selling Price","Operating Cost")) -> Operating Cost
A13: Jan-25 | B13: ='Budget vs Actual'!C13 -> 2770198.7 | C13: ='Budget vs Actual'!D13 -> 2469819.4 | D13: =C13-B13 -> -300379.31 | E13: =IFERROR(D13/B13,"") -> -0.10843241 | F13: =SUMPRODUCT(('Revenue Planning'!$A$4:$A$51=A13)*('Revenue Planning'!$G$4:$G$51-'Revenue Planning'!$D$4:$D$51)*'Revenue Planning'!$E$4:$E$51) -> -288040.51 | G13: =SUMPRODUCT(('Revenue Planning'!$A$4:$A$51=A13)*('Revenue Planning'!$H$4:$H$51-'Revenue Planning'!$E$4:$E$51)*'Revenue Planning'!$G$4:$G$51) -> -12338.8 | H13: ='Budget vs Actual'!H13 -> 2354496.4 | I13: ='Budget vs Actual'!I13 -> 2206679.6 | J13: =I13-H13 -> -147816.79 | K13: =IFERROR(J13/H13,"") -> -0.062780639 | L13: ='Budget vs Actual'!M13 -> 415702.25 | M13: ='Budget vs Actual'!N13 -> 263139.73 | N13: =M13-L13 -> -152562.52 | O13: =IFERROR(N13/L13,"") -> -0.3669995 | P13: =IF(N13>=0,"Favourable","Unfavourable") -> Unfavourable | Q13: =IF(AND(ABS(F13)>=ABS(G13),ABS(F13)>=ABS(J13)),"Sales Volume",IF(AND(ABS(G13)>ABS(F13),ABS(G13)>=ABS(J13)),"Selling Price","Operating Cost")) -> Sales Volume
A14: Feb-25 | B14: ='Budget vs Actual'!C14 -> 2836900.5 | C14: ='Budget vs Actual'!D14 -> 2830605.6 | D14: =C14-B14 -> -6294.88 | E14: =IFERROR(D14/B14,"") -> -0.0022189287 | F14: =SUMPRODUCT(('Revenue Planning'!$A$4:$A$51=A14)*('Revenue Planning'!$G$4:$G$51-'Revenue Planning'!$D$4:$D$51)*'Revenue Planning'!$E$4:$E$51) -> 3573.06 | G14: =SUMPRODUCT(('Revenue Planning'!$A$4:$A$51=A14)*('Revenue Planning'!$H$4:$H$51-'Revenue Planning'!$E$4:$E$51)*'Revenue Planning'!$G$4:$G$51) -> -9867.94 | H14: ='Budget vs Actual'!H14 -> 2397655.3 | I14: ='Budget vs Actual'!I14 -> 2390328.8 | J14: =I14-H14 -> -7326.46 | K14: =IFERROR(J14/H14,"") -> -0.003055677 | L14: ='Budget vs Actual'!M14 -> 439245.23 | M14: ='Budget vs Actual'!N14 -> 440276.81 | N14: =M14-L14 -> 1031.58 | O14: =IFERROR(N14/L14,"") -> 0.0023485287 | P14: =IF(N14>=0,"Favourable","Unfavourable") -> Favourable | Q14: =IF(AND(ABS(F14)>=ABS(G14),ABS(F14)>=ABS(J14)),"Sales Volume",IF(AND(ABS(G14)>ABS(F14),ABS(G14)>=ABS(J14)),"Selling Price","Operating Cost")) -> Selling Price
A15: Mar-25 | B15: ='Budget vs Actual'!C15 -> 3056072.8 | C15: ='Budget vs Actual'!D15 -> 3028929.7 | D15: =C15-B15 -> -27143.02 | E15: =IFERROR(D15/B15,"") -> -0.0088816668 | F15: =SUMPRODUCT(('Revenue Planning'!$A$4:$A$51=A15)*('Revenue Planning'!$G$4:$G$51-'Revenue Planning'!$D$4:$D$51)*'Revenue Planning'!$E$4:$E$51) -> -27159.38 | G15: =SUMPRODUCT(('Revenue Planning'!$A$4:$A$51=A15)*('Revenue Planning'!$H$4:$H$51-'Revenue Planning'!$E$4:$E$51)*'Revenue Planning'!$G$4:$G$51) -> 16.36 | H15: ='Budget vs Actual'!H15 -> 2534445.1 | I15: ='Budget vs Actual'!I15 -> 2524317 | J15: =I15-H15 -> -10128.076 | K15: =IFERROR(J15/H15,"") -> -0.0039961712 | L15: ='Budget vs Actual'!M15 -> 521627.7 | M15: ='Budget vs Actual'!N15 -> 504612.76 | N15: =M15-L15 -> -17014.944 | O15: =IFERROR(N15/L15,"") -> -0.032618942 | P15: =IF(N15>=0,"Favourable","Unfavourable") -> Unfavourable | Q15: =IF(AND(ABS(F15)>=ABS(G15),ABS(F15)>=ABS(J15)),"Sales Volume",IF(AND(ABS(G15)>ABS(F15),ABS(G15)>=ABS(J15)),"Selling Price","Operating Cost")) -> Sales Volume
A17: Volume Variance = (Actual Volume - Budget Volume) x Budget ASP, summed across all 4 categories for the month. Price Variance = (Actual ASP - Budget ASP) x Actual Volume, summed across all 4 categories. Volume + Price Variance approximates the total Revenue Variance (a small joint volume-price interaction term is not separately shown). 'Likely Driver' flags whichever of Sales Volume, Selling Price or Operating Cost has the largest absolute variance that month.

Sheet Profit Planning
A1: PROFIT PLANNING | Contribution Margin Model (Revenue - Variable Costs = Contribution - Fixed Costs = Net Profit)
A3: BUDGET | I3: ACTUAL
A4: Month | B4: Revenue | C4: Variable Costs | D4: Contribution | E4: Contribution Margin % | F4: Fixed Costs | G4: Net Profit | J4: Variable Costs | K4: Contribution | L4: Contribution Margin % | M4: Fixed Costs | N4: Net Profit
A5: Apr-24 | B5: =SUMIF('Revenue Planning'!$A$4:$A$51,A5,'Revenue Planning'!$F$4:$F$51) -> 2861000 | C5: =SUMIF('Revenue Planning'!$A$4:$A$51,A5,'Revenue Planning'!$N$4:$N$51)+SUMIFS('Expense Budget'!$E$4:$E$111,'Expense Budget'!$A$4:$A$111,A5,'Expense Budget'!$D$4:$D$111,"Variable") -> 1945400 | D5: =B5-C5 -> 915600 | E5: =IFERROR(D5/B5,"") -> 0.32002796 | F5: =SUMIFS('Expense Budget'!$E$4:$E$111,'Expense Budget'!$A$4:$A$111,A5,'Expense Budget'!$D$4:$D$111,"Fixed") -> 426000 | G5: =D5-F5 -> 489600 | I5: =SUMIF('Revenue Planning'!$A$4:$A$51,A5,'Revenue Planning'!$I$4:$I$51) -> 2874061.9 | J5: =SUMIF('Revenue Planning'!$A$4:$A$51,A5,'Revenue Planning'!$P$4:$P$51)+SUMIFS('Expense Budget'!$F$4:$F$111,'Expense Budget'!$A$4:$A$111,A5,'Expense Budget'!$D$4:$D$111,"Variable") -> 1944126.5 | K5: =I5-J5 -> 929935.45 | L5: =IFERROR(K5/I5,"") -> 0.32356138 | M5: =SUMIFS('Expense Budget'!$F$4:$F$111,'Expense Budget'!$A$4:$A$111,A5,'Expense Budget'!$D$4:$D$111,"Fixed") -> 427022 | N5: =K5-M5 -> 502913.45
A6: May-24 | B6: =SUMIF('Revenue Planning'!$A$4:$A$51,A6,'Revenue Planning'!$F$4:$F$51) -> 2978440.7 | C6: =SUMIF('Revenue Planning'!$A$4:$A$51,A6,'Revenue Planning'!$N$4:$N$51)+SUMIFS('Expense Budget'!$E$4:$E$111,'Expense Budget'!$A$4:$A$111,A6,'Expense Budget'!$D$4:$D$111,"Variable") -> 2017615.9 | D6: =B6-C6 -> 960824.8 | E6: =IFERROR(D6/B6,"") -> 0.32259323 | F6: =SUMIFS('Expense Budget'!$E$4:$E$111,'Expense Budget'!$A$4:$A$111,A6,'Expense Budget'!$D$4:$D$111,"Fixed") -> 428556 | G6: =D6-F6 -> 532268.8 | I6: =SUMIF('Revenue Planning'!$A$4:$A$51,A6,'Revenue Planning'!$I$4:$I$51) -> 2956844.2 | J6: =SUMIF('Revenue Planning'!$A$4:$A$51,A6,'Revenue Planning'!$P$4:$P$51)+SUMIFS('Expense Budget'!$F$4:$F$111,'Expense Budget'!$A$4:$A$111,A6,'Expense Budget'!$D$4:$D$111,"Variable") -> 2003008.1 | K6: =I6-J6 -> 953836.09 | L6: =IFERROR(K6/I6,"") -> 0.32258585 | M6: =SUMIFS('Expense Budget'!$F$4:$F$111,'Expense Budget'!$A$4:$A$111,A6,'Expense Budget'!$D$4:$D$111,"Fixed") -> 434703 | N6: =K6-M6 -> 519133.09
A7: Jun-24 | B7: =SUMIF('Revenue Planning'!$A$4:$A$51,A7,'Revenue Planning'!$F$4:$F$51) -> 2943903.8 | C7: =SUMIF('Revenue Planning'!$A$4:$A$51,A7,'Revenue Planning'!$N$4:$N$51)+SUMIFS('Expense Budget'!$E$4:$E$111,'Expense Budget'!$A$4:$A$111,A7,'Expense Budget'!$D$4:$D$111,"Variable") -> 1997941.6 | D7: =B7-C7 -> 945962.2 | E7: =IFERROR(D7/B7,"") -> 0.32132919 | F7: =SUMIFS('Expense Budget'!$E$4:$E$111,'Expense Budget'!$A$4:$A$111,A7,'Expense Budget'!$D$4:$D$111,"Fixed") -> 431112 | G7: =D7-F7 -> 514850.2 | I7: =SUMIF('Revenue Planning'!$A$4:$A$51,A7,'Revenue Planning'!$I$4:$I$51) -> 2920238.2 | J7: =SUMIF('Revenue Planning'!$A$4:$A$51,A7,'Revenue Planning'!$P$4:$P$51)+SUMIFS('Expense Budget'!$F$4:$F$111,'Expense Budget'!$A$4:$A$111,A7,'Expense Budget'!$D$4:$D$111,"Variable") -> 2017963 | K7: =I7-J7 -> 902275.28 | L7: =IFERROR(K7/I7,"") -> 0.30897317 | M7: =SUMIFS('Expense Budget'!$F$4:$F$111,'Expense Budget'!$A$4:$A$111,A7,'Expense Budget'!$D$4:$D$111,"Fixed") -> 429526 | N7: =K7-M7 -> 472749.28
A8: Jul-24 | B8: =SUMIF('Revenue Planning'!$A$4:$A$51,A8,'Revenue Planning'!$F$4:$F$51) -> 2742367 | C8: =SUMIF('Revenue Planning'!$A$4:$A$51,A8,'Revenue Planning'!$N$4:$N$51)+SUMIFS('Expense Budget'!$E$4:$E$111,'Expense Budget'!$A$4:$A$111,A8,'Expense Budget'!$D$4:$D$111,"Variable") -> 1879214.6 | D8: =B8-C8 -> 863152.43 | E8: =IFERROR(D8/B8,"") -> 0.31474724 | F8: =SUMIFS('Expense Budget'!$E$4:$E$111,'Expense Budget'!$A$4:$A$111,A8,'Expense Budget'!$D$4:$D$111,"Fixed") -> 433668 | G8: =D8-F8 -> 429484.43 | I8: =SUMIF('Revenue Planning'!$A$4:$A$51,A8,'Revenue Planning'!$I$4:$I$51) -> 2661268.9 | J8: =SUMIF('Revenue Planning'!$A$4:$A$51,A8,'Revenue Planning'!$P$4:$P$51)+SUMIFS('Expense Budget'!$F$4:$F$111,'Expense Budget'!$A$4:$A$111,A8,'Expense Budget'!$D$4:$D$111,"Variable") -> 1863464 | K8: =I8-J8 -> 797804.85 | L8: =IFERROR(K8/I8,"") -> 0.29978363 | M8: =SUMIFS('Expense Budget'!$F$4:$F$111,'Expense Budget'!$A$4:$A$111,A8,'Expense Budget'!$D$4:$D$111,"Fixed") -> 437228 | N8: =K8-M8 -> 360576.85
A9: Aug-24 | B9: =SUMIF('Revenue Planning'!$A$4:$A$51,A9,'Revenue Planning'!$F$4:$F$51) -> 2743148.7 | C9: =SUMIF('Revenue Planning'!$A$4:$A$51,A9,'Revenue Planning'!$N$4:$N$51)+SUMIFS('Expense Budget'!$E$4:$E$111,'Expense Budget'!$A$4:$A$111,A9,'Expense Budget'!$D$4:$D$111,"Variable") -> 1881467.4 | D9: =B9-C9 -> 861681.33 | E9: =IFERROR(D9/B9,"") -> 0.31412126 | F9: =SUMIFS('Expense Budget'!$E$4:$E$111,'Expense Budget'!$A$4:$A$111,A9,'Expense Budget'!$D$4:$D$111,"Fixed") -> 436224 | G9: =D9-F9 -> 425457.33 | I9: =SUMIF('Revenue Planning'!$A$4:$A$51,A9,'Revenue Planning'!$I$4:$I$51) -> 2611563.2 | J9: =SUMIF('Revenue Planning'!$A$4:$A$51,A9,'Revenue Planning'!$P$4:$P$51)+SUMIFS('Expense Budget'!$F$4:$F$111,'Expense Budget'!$A$4:$A$111,A9,'Expense Budget'!$D$4:$D$111,"Variable") -> 1844291.8 | K9: =I9-J9 -> 767271.39 | L9: =IFERROR(K9/I9,"") -> 0.29379775 | M9: =SUMIFS('Expense Budget'!$F$4:$F$111,'Expense Budget'!$A$4:$A$111,A9,'Expense Budget'!$D$4:$D$111,"Fixed") -> 438618 | N9: =K9-M9 -> 328653.39
A10: Sep-24 | B10: =SUMIF('Revenue Planning'!$A$4:$A$51,A10,'Revenue Planning'!$F$4:$F$51) -> 2843333.8 | C10: =SUMIF('Revenue Planning'!$A$4:$A$51,A10,'Revenue Planning'!$N$4:$N$51)+SUMIFS('Expense Budget'!$E$4:$E$111,'Expense Budget'!$A$4:$A$111,A10,'Expense Budget'!$D$4:$D$111,"Variable") -> 1944537.2 | D10: =B10-C10 -> 898796.58 | E10: =IFERROR(D10/B10,"") -> 0.3161066 | F10: =SUMIFS('Expense Budget'!$E$4:$E$111,'Expense Budget'!$A$4:$A$111,A10,'Expense Budget'!$D$4:$D$111,"Fixed") -> 438780 | G10: =D10-F10 -> 460016.58 | I10: =SUMIF('Revenue Planning'!$A$4:$A$51,A10,'Revenue Planning'!$I$4:$I$51) -> 2826123.7 | J10: =SUMIF('Revenue Planning'!$A$4:$A$51,A10,'Revenue Planning'!$P$4:$P$51)+SUMIFS('Expense Budget'!$F$4:$F$111,'Expense Budget'!$A$4:$A$111,A10,'Expense Budget'!$D$4:$D$111,"Variable") -> 1923423.3 | K10: =I10-J10 -> 902700.41 | L10: =IFERROR(K10/I10,"") -> 0.31941292 | M10: =SUMIFS('Expense Budget'!$F$4:$F$111,'Expense Budget'!$A$4:$A$111,A10,'Expense Budget'!$D$4:$D$111,"Fixed") -> 440645 | N10: =K10-M10 -> 462055.41
A11: Oct-24 | B11: =SUMIF('Revenue Planning'!$A$4:$A$51,A11,'Revenue Planning'!$F$4:$F$51) -> 3308101.5 | C11: =SUMIF('Revenue Planning'!$A$4:$A$51,A11,'Revenue Planning'!$N$4:$N$51)+SUMIFS('Expense Budget'!$E$4:$E$111,'Expense Budget'!$A$4:$A$111,A11,'Expense Budget'!$D$4:$D$111,"Variable") -> 2264004.5 | D11: =B11-C11 -> 1044097 | E11: =IFERROR(D11/B11,"") -> 0.31561817 | F11: =SUMIFS('Expense Budget'!$E$4:$E$111,'Expense Budget'!$A$4:$A$111,A11,'Expense Budget'!$D$4:$D$111,"Fixed") -> 441336 | G11: =D11-F11 -> 602760.95 | I11: =SUMIF('Revenue Planning'!$A$4:$A$51,A11,'Revenue Planning'!$I$4:$I$51) -> 3579618.2 | J11: =SUMIF('Revenue Planning'!$A$4:$A$51,A11,'Revenue Planning'!$P$4:$P$51)+SUMIFS('Expense Budget'!$F$4:$F$111,'Expense Budget'!$A$4:$A$111,A11,'Expense Budget'!$D$4:$D$111,"Variable") -> 2430801.4 | K11: =I11-J11 -> 1148816.9 | L11: =IFERROR(K11/I11,"") -> 0.32093279 | M11: =SUMIFS('Expense Budget'!$F$4:$F$111,'Expense Budget'!$A$4:$A$111,A11,'Expense Budget'!$D$4:$D$111,"Fixed") -> 438669 | N11: =K11-M11 -> 710147.88
A12: Nov-24 | B12: =SUMIF('Revenue Planning'!$A$4:$A$51,A12,'Revenue Planning'!$F$4:$F$51) -> 3456789.7 | C12: =SUMIF('Revenue Planning'!$A$4:$A$51,A12,'Revenue Planning'!$N$4:$N$51)+SUMIFS('Expense Budget'!$E$4:$E$111,'Expense Budget'!$A$4:$A$111,A12,'Expense Budget'!$D$4:$D$111,"Variable") -> 2360592.3 | D12: =B12-C12 -> 1096197.3 | E12: =IFERROR(D12/B12,"") -> 0.31711427 | F12: =SUMIFS('Expense Budget'!$E$4:$E$111,'Expense Budget'!$A$4:$A$111,A12,'Expense Budget'!$D$4:$D$111,"Fixed") -> 443892 | G12: =D12-F12 -> 652305.33 | I12: =SUMIF('Revenue Planning'!$A$4:$A$51,A12,'Revenue Planning'!$I$4:$I$51) -> 3669694.4 | J12: =SUMIF('Revenue Planning'!$A$4:$A$51,A12,'Revenue Planning'!$P$4:$P$51)+SUMIFS('Expense Budget'!$F$4:$F$111,'Expense Budget'!$A$4:$A$111,A12,'Expense Budget'!$D$4:$D$111,"Variable") -> 2489253 | K12: =I12-J12 -> 1180441.4 | L12: =IFERROR(K12/I12,"") -> 0.32167295 | M12: =SUMIFS('Expense Budget'!$F$4:$F$111,'Expense Budget'!$A$4:$A$111,A12,'Expense Budget'!$D$4:$D$111,"Fixed") -> 443444 | N12: =K12-M12 -> 736997.43
A13: Dec-24 | B13: =SUMIF('Revenue Planning'!$A$4:$A$51,A13,'Revenue Planning'!$F$4:$F$51) -> 3144592.9 | C13: =SUMIF('Revenue Planning'!$A$4:$A$51,A13,'Revenue Planning'!$N$4:$N$51)+SUMIFS('Expense Budget'!$E$4:$E$111,'Expense Budget'!$A$4:$A$111,A13,'Expense Budget'!$D$4:$D$111,"Variable") -> 2134786.8 | D13: =B13-C13 -> 1009806.1 | E13: =IFERROR(D13/B13,"") -> 0.32112458 | F13: =SUMIFS('Expense Budget'!$E$4:$E$111,'Expense Budget'!$A$4:$A$111,A13,'Expense Budget'!$D$4:$D$111,"Fixed") -> 446448 | G13: =D13-F13 -> 563358.06 | I13: =SUMIF('Revenue Planning'!$A$4:$A$51,A13,'Revenue Planning'!$I$4:$I$51) -> 3131491 | J13: =SUMIF('Revenue Planning'!$A$4:$A$51,A13,'Revenue Planning'!$P$4:$P$51)+SUMIFS('Expense Budget'!$F$4:$F$111,'Expense Budget'!$A$4:$A$111,A13,'Expense Budget'!$D$4:$D$111,"Variable") -> 2114245 | K13: =I13-J13 -> 1017246 | L13: =IFERROR(K13/I13,"") -> 0.32484398 | M13: =SUMIFS('Expense Budget'!$F$4:$F$111,'Expense Budget'!$A$4:$A$111,A13,'Expense Budget'!$D$4:$D$111,"Fixed") -> 449505 | N13: =K13-M13 -> 567740.97
A14: Jan-25 | B14: =SUMIF('Revenue Planning'!$A$4:$A$51,A14,'Revenue Planning'!$F$4:$F$51) -> 2770198.7 | C14: =SUMIF('Revenue Planning'!$A$4:$A$51,A14,'Revenue Planning'!$N$4:$N$51)+SUMIFS('Expense Budget'!$E$4:$E$111,'Expense Budget'!$A$4:$A$111,A14,'Expense Budget'!$D$4:$D$111,"Variable") -> 1905492.4 | D14: =B14-C14 -> 864706.25 | E14: =IFERROR(D14/B14,"") -> 0.31214593 | F14: =SUMIFS('Expense Budget'!$E$4:$E$111,'Expense Budget'!$A$4:$A$111,A14,'Expense Budget'!$D$4:$D$111,"Fixed") -> 449004 | G14: =D14-F14 -> 415702.25 | I14: =SUMIF('Revenue Planning'!$A$4:$A$51,A14,'Revenue Planning'!$I$4:$I$51) -> 2469819.4 | J14: =SUMIF('Revenue Planning'!$A$4:$A$51,A14,'Revenue Planning'!$P$4:$P$51)+SUMIFS('Expense Budget'!$F$4:$F$111,'Expense Budget'!$A$4:$A$111,A14,'Expense Budget'!$D$4:$D$111,"Variable") -> 1753378.6 | K14: =I14-J14 -> 716440.73 | L14: =IFERROR(K14/I14,"") -> 0.29007819 | M14: =SUMIFS('Expense Budget'!$F$4:$F$111,'Expense Budget'!$A$4:$A$111,A14,'Expense Budget'!$D$4:$D$111,"Fixed") -> 453301 | N14: =K14-M14 -> 263139.73
A15: Feb-25 | B15: =SUMIF('Revenue Planning'!$A$4:$A$51,A15,'Revenue Planning'!$F$4:$F$51) -> 2836900.5 | C15: =SUMIF('Revenue Planning'!$A$4:$A$51,A15,'Revenue Planning'!$N$4:$N$51)+SUMIFS('Expense Budget'!$E$4:$E$111,'Expense Budget'!$A$4:$A$111,A15,'Expense Budget'!$D$4:$D$111,"Variable") -> 1946095.3 | D15: =B15-C15 -> 890805.23 | E15: =IFERROR(D15/B15,"") -> 0.31400651 | F15: =SUMIFS('Expense Budget'!$E$4:$E$111,'Expense Budget'!$A$4:$A$111,A15,'Expense Budget'!$D$4:$D$111,"Fixed") -> 451560 | G15: =D15-F15 -> 439245.23 | I15: =SUMIF('Revenue Planning'!$A$4:$A$51,A15,'Revenue Planning'!$I$4:$I$51) -> 2830605.6 | J15: =SUMIF('Revenue Planning'!$A$4:$A$51,A15,'Revenue Planning'!$P$4:$P$51)+SUMIFS('Expense Budget'!$F$4:$F$111,'Expense Budget'!$A$4:$A$111,A15,'Expense Budget'!$D$4:$D$111,"Variable") -> 1935788.8 | K15: =I15-J15 -> 894816.81 | L15: =IFERROR(K15/I15,"") -> 0.31612203 | M15: =SUMIFS('Expense Budget'!$F$4:$F$111,'Expense Budget'!$A$4:$A$111,A15,'Expense Budget'!$D$4:$D$111,"Fixed") -> 454540 | N15: =K15-M15 -> 440276.81
A16: Mar-25 | B16: =SUMIF('Revenue Planning'!$A$4:$A$51,A16,'Revenue Planning'!$F$4:$F$51) -> 3056072.8 | C16: =SUMIF('Revenue Planning'!$A$4:$A$51,A16,'Revenue Planning'!$N$4:$N$51)+SUMIFS('Expense Budget'!$E$4:$E$111,'Expense Budget'!$A$4:$A$111,A16,'Expense Budget'!$D$4:$D$111,"Variable") -> 2080329.1 | D16: =B16-C16 -> 975743.7 | E16: =IFERROR(D16/B16,"") -> 0.31928026 | F16: =SUMIFS('Expense Budget'!$E$4:$E$111,'Expense Budget'!$A$4:$A$111,A16,'Expense Budget'!$D$4:$D$111,"Fixed") -> 454116 | G16: =D16-F16 -> 521627.7 | I16: =SUMIF('Revenue Planning'!$A$4:$A$51,A16,'Revenue Planning'!$I$4:$I$51) -> 3028929.7 | J16: =SUMIF('Revenue Planning'!$A$4:$A$51,A16,'Revenue Planning'!$P$4:$P$51)+SUMIFS('Expense Budget'!$F$4:$F$111,'Expense Budget'!$A$4:$A$111,A16,'Expense Budget'!$D$4:$D$111,"Variable") -> 2066315 | K16: =I16-J16 -> 962614.76 | L16: =IFERROR(K16/I16,"") -> 0.31780689 | M16: =SUMIFS('Expense Budget'!$F$4:$F$111,'Expense Budget'!$A$4:$A$111,A16,'Expense Budget'!$D$4:$D$111,"Fixed") -> 458002 | N16: =K16-M16 -> 504612.76
A17: FY 2024-25 Total | B17: =SUM(B5:B16) -> 35684850 | C17: =SUM(C5:C16) -> 24357477 | D17: =SUM(D5:D16) -> 11327373 | E17: =IFERROR(D17/B17,"") -> 0.31742807 | F17: =SUM(F5:F16) -> 5280696 | G17: =SUM(G5:G16) -> 6046676.9 | I17: =SUM(I5:I16) -> 35560258 | J17: =SUM(J5:J16) -> 24386058 | K17: =SUM(K5:K16) -> 11174200 | L17: =IFERROR(K17/I17,"") -> 0.31423281 | M17: =SUM(M5:M16) -> 5305203 | N17: =SUM(N5:N16) -> 5868997
A19: Variable Costs = Cost of Goods Sold (COGS) + variable-classified operating expenses (Utilities, Marketing, Transportation, Maintenance, Other Operating Expenses). Fixed Costs = Salaries, Rent, Technology, Office Expenses. This model assumes no interest or tax expense, so Net Profit shown here equals Operating Profit.

Sheet Financial Forecast
A1: FINANCIAL FORECAST | Last 3 Months Actual (Context) + 6-Month Forward Forecast (Apr-25 to Sep-25)
A3: Forecast Methodology
A4: Method: Trend-based forecasting. For each revenue category and each expense category, the average month-on-month growth rate is calculated from the 12 months of FY 2024-25 Actuals, then applied forward month by month from the Mar-25 actual base. The growth rate is capped to a realistic range (revenue: -1% to +3% per month; expenses: -1% to +2% per month) to avoid compounding outlier months. COGS is forecast using each category's average actual COGS-to-revenue ratio for FY 2024-25.
A5: Key assumptions: product mix, pricing strategy and cost structure remain broadly similar to FY 2024-25; no major new product launch, competitor action or input-cost shock is factored in.
A6: Limitations: a simple trend/average-growth model does not capture demand shocks (e.g. festive spikes), so it should be read as a directional planning estimate, not a guaranteed outcome. It also does not model financing, tax or one-off costs.
A8: Month | B8: Period Type | C8: Revenue | D8: Expense (incl. COGS) | E8: Net Profit | F8: Net Profit Margin % | G8: MoM Revenue Growth %
A9: Jan-25 | B9: Actual | C9: ='Budget vs Actual'!D13 -> 2469819.4 | D9: ='Budget vs Actual'!I13 -> 2206679.6 | E9: =C9-D9 -> 263139.73 | F9: =IFERROR(E9/C9,"") -> 0.1065421 | G9: =IF(ROW()=9,"",IFERROR(C9/C8-1,""))
A10: Feb-25 | B10: Actual | C10: ='Budget vs Actual'!D14 -> 2830605.6 | D10: ='Budget vs Actual'!I14 -> 2390328.8 | E10: =C10-D10 -> 440276.81 | F10: =IFERROR(E10/C10,"") -> 0.15554156 | G10: =IF(ROW()=9,"",IFERROR(C10/C9-1,"")) -> 0.14607799
A11: Mar-25 | B11: Actual | C11: ='Budget vs Actual'!D15 -> 3028929.7 | D11: ='Budget vs Actual'!I15 -> 2524317 | E11: =C11-D11 -> 504612.76 | F11: =IFERROR(E11/C11,"") -> 0.16659771 | G11: =IF(ROW()=9,"",IFERROR(C11/C10-1,"")) -> 0.070064201
A12: Apr-25 | B12: Forecast | C12: =SUMIF('Revenue Planning'!$A$52:$A$75,A12,'Revenue Planning'!$J$52:$J$75) -> 3072815.8 | D12: =SUMIF('Expense Budget'!$A$135:$A$188,A12,'Expense Budget'!$F$135:$F$188)+SUMIF('Revenue Planning'!$A$52:$A$75,A12,'Revenue Planning'!$Q$52:$Q$75) -> 2561280.6 | E12: =C12-D12 -> 511535.19 | F12: =IFERROR(E12/C12,"") -> 0.16647115 | G12: =IFERROR(C12/C11-1,"") -> 0.014488973
A13: May-25 | B13: Forecast | C13: =SUMIF('Revenue Planning'!$A$52:$A$75,A13,'Revenue Planning'!$J$52:$J$75) -> 3117364 | D13: =SUMIF('Expense Budget'!$A$135:$A$188,A13,'Expense Budget'!$F$135:$F$188)+SUMIF('Revenue Planning'!$A$52:$A$75,A13,'Revenue Planning'!$Q$52:$Q$75) -> 2594139.6 | E13: =C13-D13 -> 523224.33 | F13: =IFERROR(E13/C13,"") -> 0.16784191 | G13: =IFERROR(C13/C12-1,"") -> 0.014497498
A14: Jun-25 | B14: Forecast | C14: =SUMIF('Revenue Planning'!$A$52:$A$75,A14,'Revenue Planning'!$J$52:$J$75) -> 3162584.6 | D14: =SUMIF('Expense Budget'!$A$135:$A$188,A14,'Expense Budget'!$F$135:$F$188)+SUMIF('Revenue Planning'!$A$52:$A$75,A14,'Revenue Planning'!$Q$52:$Q$75) -> 2627463.7 | E14: =C14-D14 -> 535120.9 | F14: =IFERROR(E14/C14,"") -> 0.16920366 | G14: =IFERROR(C14/C13-1,"") -> 0.014506048
A15: Jul-25 | B15: Forecast | C15: =SUMIF('Revenue Planning'!$A$52:$A$75,A15,'Revenue Planning'!$J$52:$J$75) -> 3208488.3 | D15: =SUMIF('Expense Budget'!$A$135:$A$188,A15,'Expense Budget'!$F$135:$F$188)+SUMIF('Revenue Planning'!$A$52:$A$75,A15,'Revenue Planning'!$Q$52:$Q$75) -> 2661259.9 | E15: =C15-D15 -> 547228.45 | F15: =IFERROR(E15/C15,"") -> 0.17055647 | G15: =IFERROR(C15/C14-1,"") -> 0.014514625
A16: Aug-25 | B16: Forecast | C16: =SUMIF('Revenue Planning'!$A$52:$A$75,A16,'Revenue Planning'!$J$52:$J$75) -> 3255085.9 | D16: =SUMIF('Expense Budget'!$A$135:$A$188,A16,'Expense Budget'!$F$135:$F$188)+SUMIF('Revenue Planning'!$A$52:$A$75,A16,'Revenue Planning'!$Q$52:$Q$75) -> 2695535.3 | E16: =C16-D16 -> 559550.53 | F16: =IFERROR(E16/C16,"") -> 0.17190039 | G16: =IFERROR(C16/C15-1,"") -> 0.014523207
A17: Sep-25 | B17: Forecast | C17: =SUMIF('Revenue Planning'!$A$52:$A$75,A17,'Revenue Planning'!$J$52:$J$75) -> 3302388.2 | D17: =SUMIF('Expense Budget'!$A$135:$A$188,A17,'Expense Budget'!$F$135:$F$188)+SUMIF('Revenue Planning'!$A$52:$A$75,A17,'Revenue Planning'!$Q$52:$Q$75) -> 2730297.4 | E17: =C17-D17 -> 572090.78 | F17: =IFERROR(E17/C17,"") -> 0.17323547 | G17: =IFERROR(C17/C16-1,"") -> 0.014531813
A18: Apr-Sep 2025 Forecast Total | C18: =SUM(C12:C17) -> 19118727 | D18: =SUM(D12:D17) -> 15869977 | E18: =C18-D18 -> 3248750.2 | F18: =IFERROR(E18/C18,"") -> 0.16992503

Sheet Scenario Analysis
A1: SCENARIO / WHAT-IF ANALYSIS | FY 2025-26 Projection off FY 2024-25 Actual Base
A3: Assumption / Output | B3: Conservative | C3: Base Case | D3: Optimistic | E3: Notes
A4: Volume Change % (input) | B4: -0.02 | C4: 0.04 | D4: 0.09 | E4: Change in units sold vs FY 2024-25 actual, by scenario
A5: Selling Price Change % (input) | B5: 0.02 | C5: 0.03 | D5: 0.04 | E5: Average selling price change vs FY 2024-25 actual
A6: Implied Revenue Growth % | B6: =(1+B4)*(1+B5)-1 -> -0.0004 | C6: =(1+C4)*(1+C5)-1 -> 0.0712 | D6: =(1+D4)*(1+D5)-1 -> 0.1336 | E6: Formula: (1+Volume%) x (1+Price%) - 1
A7: Expense Growth % (input) | B7: 0.05 | C7: 0.06 | D7: 0.07 | E7: Growth in total operating expenses (incl. COGS ratio held constant)
A8: Base Revenue - FY 2024-25 Actual (Rs.) | B8: ='Budget vs Actual'!D16 -> 35560258 | C8: ='Budget vs Actual'!D16 -> 35560258 | D8: ='Budget vs Actual'!D16 -> 35560258 | E8: Reference: 'Budget vs Actual' FY Total Actual Revenue
A9: Projected Revenue (Rs.) | B9: =B8*(1+B6) -> 35546034 | C9: =C8*(1+C6) -> 38092149 | D9: =D8*(1+D6) -> 40311109 | E9: Base Revenue x (1 + Implied Revenue Growth %)
A10: Base Total Cost - FY 2024-25 Actual (Rs.) | B10: ='Budget vs Actual'!I16 -> 29691261 | C10: ='Budget vs Actual'!I16 -> 29691261 | D10: ='Budget vs Actual'!I16 -> 29691261 | E10: COGS + Operating Expenses, FY 2024-25 Actual
A11: Projected Total Cost (Rs.) | B11: =B10*(1+B7) -> 31175824 | C11: =C10*(1+C7) -> 31472737 | D11: =D10*(1+D7) -> 31769650 | E11: Base Total Cost x (1 + Expense Growth %)
A12: Projected Net Profit (Rs.) | B12: =B9-B11 -> 4370209.9 | C12: =C9-C11 -> 6619411.8 | D12: =D9-D11 -> 8541459.3 | E12: Projected Revenue - Projected Total Cost
A13: Projected Net Profit Margin % | B13: =IFERROR(B12/B9,"") -> 0.12294508 | C13: =IFERROR(C12/C9,"") -> 0.17377365 | D13: =IFERROR(D12/D9,"") -> 0.21188847 | E13: Projected Net Profit / Projected Revenue
A15: Blue cells are editable scenario levers. Change Volume %, Price %, or Expense Growth % for any scenario and every downstream figure recalculates. Base figures are FY 2024-25 Actuals (Revenue Planning / Expense Budget). COGS-to-revenue ratio is assumed to stay at the FY 2024-25 blended level within each scenario's projected total cost.

Sheet Break-Even Analysis
A1: BREAK-EVEN ANALYSIS | FY 2024-25 Actual Basis (Blended Product Mix)
A3: Metric | B3: Value | C3: Notes
A4: Actual Revenue (Rs.) | B4: ='Profit Planning'!I17 -> 35560258 | C4: FY 2024-25 Total Actual Revenue
A5: Actual Variable Costs (Rs.) | B5: ='Profit Planning'!J17 -> 24386058 | C5: COGS + variable operating expenses
A6: Contribution Margin (Rs.) | B6: =B4-B5 -> 11174200 | C6: Revenue - Variable Costs
A7: Contribution Margin Ratio | B7: =IFERROR(B6/B4,"") -> 0.31423281 | C7: Contribution Margin / Revenue
A8: Actual Fixed Costs (Rs.) | B8: ='Profit Planning'!M17 -> 5305203 | C8: FY 2024-25 Total Actual Fixed Costs
A9: Break-Even Revenue (Rs.) | B9: =IFERROR(B8/B7,"") -> 16883033 | C9: Fixed Costs / Contribution Margin Ratio
A10: Total Actual Volume (units) | B10: =SUM('Revenue Planning'!G4:G51) -> 877616 | C10: Sum of all 4 categories, FY 2024-25 Actual
A11: Blended Avg Selling Price (Rs./unit) | B11: =IFERROR(B4/B10,"") -> 40.519155 | C11: Actual Revenue / Total Actual Volume
A12: Blended Avg Variable Cost (Rs./unit) | B12: =IFERROR(B5/B10,"") -> 27.786707 | C12: Actual Variable Costs / Total Actual Volume
A13: Break-Even Volume (units) | B13: =IFERROR(B8/(B11-B12),"") -> 416667.95 | C13: Fixed Costs / (Avg Selling Price - Avg Variable Cost per unit)
A14: Actual Revenue vs Break-Even (Margin of Safety, Rs.) | B14: =B4-B9 -> 18677225 | C14: Actual Revenue - Break-Even Revenue
A15: Margin of Safety % | B15: =IFERROR(B14/B4,"") -> 0.52522749 | C15: Margin of Safety Rs. / Actual Revenue
A17: Assumptions: (1) Blended figures assume the FY 2024-25 actual product mix and cost structure hold steady - break-even for an individual product would differ. (2) Fixed costs are treated as fixed within the FY 2024-25 operating range; a large change in scale could shift some 'fixed' costs (e.g. additional staff or space).

Sheet Target Profit Analysis
A1: TARGET PROFIT ANALYSIS | Revenue Required to Achieve a Management Profit Target (FY 2025-26 Planning)
A3: Metric | B3: Value | C3: Notes
A4: Current Revenue - FY 2024-25 Actual (Rs.) | B4: ='Break-Even Analysis'!B4 -> 35560258 | C4: Reference base
A5: Current Net Profit - FY 2024-25 Actual (Rs.) | B5: ='Profit Planning'!N17 -> 5868997 | C5: Reference base
A6: Contribution Margin Ratio | B6: ='Break-Even Analysis'!B7 -> 0.31423281 | C6: From Break-Even Analysis
A7: Fixed Costs (Rs.) | B7: ='Break-Even Analysis'!B8 -> 5305203 | C7: From Break-Even Analysis
A8: Target Profit (Rs.) - input | B8: 7500000 | C8: Management target for FY 2025-26 (editable input)
A9: Required Revenue (Rs.) | B9: =(B7+B8)/B6 -> 40750687 | C9: (Fixed Costs + Target Profit) / Contribution Margin Ratio
A10: Additional Revenue Required (Rs.) | B10: =B9-B4 -> 5190428.5 | C10: Required Revenue - Current Revenue
A11: Additional Revenue Required (%) | B11: =IFERROR(B10/B4,"") -> 0.1459615 | C11: Additional Revenue Required / Current Revenue
A13: Change the Target Profit input (yellow cell) to see the Required Revenue recalculate instantly. The model assumes the FY 2024-25 blended Contribution Margin Ratio holds - a materially different product mix would change the ratio and result.

Sheet Financial KPIs
A1: FINANCIAL KPIs | FY 2024-25 Actual Performance
A3: KPI | B3: Value | C3: Calculation
A4: Revenue Growth % (H2 vs H1 FY 2024-25) | B4: =IFERROR((SUM('Budget vs Actual'!D10:D15)/SUM('Budget vs Actual'!D4:D9))-1,"") -> 0.11038856 | C4: 2nd-half Actual Revenue vs 1st-half Actual Revenue
A5: Gross Profit Margin % (Actual) | B5: =IFERROR(('Profit Planning'!I17-SUM('Revenue Planning'!P4:P51))/'Profit Planning'!I17,"") -> 0.37303745 | C5: (Revenue - COGS) / Revenue
A6: Operating Margin % (Actual) | B6: =IFERROR('Profit Planning'!N17/'Profit Planning'!I17,"") -> 0.16504371 | C6: Net Profit / Revenue (no separate financing/tax layer modelled)
A7: Net Profit Margin % (Actual) | B7: =IFERROR('Profit Planning'!N17/'Profit Planning'!I17,"") -> 0.16504371 | C7: Net Profit / Revenue
A8: Expense Ratio % (Actual, incl. COGS) | B8: =IFERROR('Budget vs Actual'!I16/'Budget vs Actual'!D16,"") -> 0.83495629 | C8: Total Expense (incl. COGS) / Revenue
A9: Budget Achievement % (Revenue) | B9: =IFERROR('Budget vs Actual'!D16/'Budget vs Actual'!C16,"") -> 0.99650856 | C9: Actual Revenue / Budget Revenue
A10: Forecast Growth % (Apr-Sep 25 vs Apr-Sep 24) | B10: =IFERROR('Financial Forecast'!C18/SUM('Budget vs Actual'!D4:D9)-1,"") -> 0.1346358 | C10: Forecast Revenue (Apr-Sep 25) / Actual Revenue (Apr-Sep 24) - 1
A11: Contribution Margin % | B11: ='Break-Even Analysis'!B7 -> 0.31423281 | C11: From Break-Even Analysis
A12: Break-Even Revenue (Rs.) | B12: ='Break-Even Analysis'!B9 -> 16883033 | C12: From Break-Even Analysis
A13: Target Profit Gap - Additional Revenue Needed (Rs.) | B13: ='Target Profit Analysis'!B10 -> 5190428.5 | C13: From Target Profit Analysis

Sheet Business Analysis
A1: BUSINESS ANALYSIS & RECOMMENDATIONS | FY 2024-25
A3: Key Data Points (formula-driven, from Revenue Planning / Expense Budget / Budget vs Actual)
A4: Metric | B4: Category / Month | C4: Value
A5: Best-performing revenue category (highest Rev. Variance %) | B5: =INDEX('Revenue Planning'!A81:A84,MATCH(MAX('Revenue Planning'!K81:K84),'Revenue Planning'!K81:K84,0)) -> Dairy Products | C5: =MAX('Revenue Planning'!K81:K84) -> 0.0053617904
A6: Weakest-performing revenue category (lowest Rev. Variance %) | B6: =INDEX('Revenue Planning'!A81:A84,MATCH(MIN('Revenue Planning'!K81:K84),'Revenue Planning'!K81:K84,0)) -> Beverages | C6: =MIN('Revenue Planning'!K81:K84) -> -0.018746199
A7: Largest expense category (by Actual Rs.) | B7: =INDEX('Expense Budget'!A117:A125,MATCH(MAX('Expense Budget'!E117:E125),'Expense Budget'!E117:E125,0)) -> Salaries | C7: =MAX('Expense Budget'!E117:E125) -> 3549486
A8: Largest unfavourable expense variance % (category) | B8: =INDEX('Expense Budget'!A117:A125,MATCH(MAX('Expense Budget'!G117:G125),'Expense Budget'!G117:G125,0)) -> Office Expenses | C8: =MAX('Expense Budget'!G117:G125) -> 0.01984063
A9: Strongest profit month (highest Profit Variance %) | B9: =INDEX('Budget vs Actual'!A4:A15,MATCH(MAX('Budget vs Actual'!P4:P15),'Budget vs Actual'!P4:P15,0)) -> Oct-24 | C9: =MAX('Budget vs Actual'!P4:P15) -> 0.1781584
A10: Weakest profit month (lowest Profit Variance %) | B10: =INDEX('Budget vs Actual'!A4:A15,MATCH(MIN('Budget vs Actual'!P4:P15),'Budget vs Actual'!P4:P15,0)) -> Jan-25 | C10: =MIN('Budget vs Actual'!P4:P15) -> -0.3669995
A12: Management Commentary
A13: REVENUE PERFORMANCE: FY 2024-25 Actual Revenue closed at Rs. 3.56 crore against a Budget of Rs. 3.57 crore (-0.35%), effectively on target for the year, but the monthly pattern hides two distinct stories. Packaged Snacks (~0.0% variance) and Dairy Products (+0.5%) met or beat budget for the year. Beverages missed budget by the widest margin (-1.9%), driven almost entirely by a monsoon-season volume shortfall in Jul-24 and Aug-24. Bakery Items was marginally short (-0.3%).
A15: SEASONAL PATTERN: Oct-24 and Nov-24 (festive season) were the strongest months, with Actual Profit beating Budget by +18% and +13% respectively - marketing spend was intentionally increased ahead of the festive period and volume response more than covered the extra cost. Jan-25 was the weakest month (Actual Profit -37% vs Budget), consistent with a post-festive demand slowdown combined with a distributor stock correction. Jul-24 and Aug-24 (monsoon) were also unfavourable (-16% and -23%), linked to lower dispatch volumes and a rise in the Dairy/Bakery input-cost ratio.
A17: EXPENSE DISCIPLINE: Total FY 2024-25 Operating Expenses were only 0.6% over budget, so overall cost control was strong. Salaries is the single largest expense line (~Rs. 35.5 lakh Actual) and ran close to budget (+0.5%). The largest percentage overrun was Office Expenses (+2.0%) and Utilities (+1.9%), both small in absolute Rs. terms. Marketing ran +1.6% over budget, concentrated in the festive months - a deliberate, revenue-linked overspend rather than a control gap.
A19: MARGIN STRUCTURE: Dairy Products carries the lowest gross margin of the four categories (~31%) due to a higher cost-of-goods ratio for perishables, versus ~38-43% for the other three categories. Since Dairy is also one of the two largest revenue categories, its margin drag is a meaningful factor in the blended FY margin - see Break-Even Analysis for the blended Contribution Margin Ratio.
A21: RECOMMENDATIONS: (1) Build a monsoon contingency into the Jul-Aug budget for Beverages and Bakery Items - volume and input-cost assumptions should be set below the FY average rather than flat, based on this year's actual pattern. (2) Treat the Oct-Nov festive marketing increase as a repeatable, budgeted play for FY 2025-26 given its proven payback. (3) Investigate the Jan-25 shortfall further before finalising the FY 2025-26 January budget - if it is a recurring post-festive pattern, budget it accordingly rather than as a flat continuation of December. (4) Review Dairy Products input-sourcing or pricing, since its lower gross margin dilutes the blended Contribution Margin Ratio used for the Break-Even and Target Profit models.
A23: All figures above are computed directly from the Revenue Planning, Expense Budget and Budget vs Actual sheets; the commentary summarises those computed results and does not introduce numbers outside the model.
